Workbook

Sheet Articles per publication year
A1: {=_xlfn.UNIQUE(VALUE(RIGHT(Articles[Publication year], 4)))} -> 2025 | B1: =COUNTIF(Articles[Publication year], "*" & A1) -> 16 | D1: {=_xlfn._xlws.SORT(A1:B6,1)} -> 2021 | E1: 2
A2: 2022 | B2: =COUNTIF(Articles[Publication year], "*" & A2) -> 7 | D2: 2022 | E2: 7
A3: 2024 | B3: =COUNTIF(Articles[Publication year], "*" & A3) -> 9 | D3: 2023 | E3: 4
A4: 2026 | B4: =COUNTIF(Articles[Publication year], "*" & A4) -> 15 | D4: 2024 | E4: 9
A5: 2021 | B5: =COUNTIF(Articles[Publication year], "*" & A5) -> 2 | D5: 2025 | E5: 16
A6: 2023 | B6: =COUNTIF(Articles[Publication year], "*" & A6) -> 4 | D6: 2026 | E6: 15

Sheet Articles per publisher
A1: {=TRIM(_xlfn.TEXTBEFORE(Articles[Repository, journal/proceeding, and publisher],", "))} -> Scopus | B1: {=TRIM(_xlfn.TEXTBEFORE(_xlfn.TEXTAFTER(Articles[Repository, journal/proceeding, and publisher], ",", 1), ",", -1))} -> Baltic Journal of Modern Computing | C1: {=TRIM(_xlfn.TEXTAFTER(Articles[Repository, journal/proceeding, and publisher], ",", -1))} -> University of Latvia | E1: {=_xlfn.UNIQUE(_xlfn.ANCHORARRAY(A1))} -> Scopus | F1: =COUNTIF(_xlfn.ANCHORARRAY($A$1),E1) -> 40 | H1: {=_xlfn._xlws.SORT(E1:F6,2,-1)} -> Scopus | I1: 40 | K1: {=_xlfn.UNIQUE(_xlfn.ANCHORARRAY(B1))} -> Baltic Journal of Modern Computing | L1: =COUNTIF(_xlfn.ANCHORARRAY($B$1),K1) -> 1 | N1: {=_xlfn.UNIQUE(_xlfn.ANCHORARRAY(C1))} -> University of Latvia | O1: =COUNTIF(_xlfn.ANCHORARRAY($C$1),N1) -> 1 | Q1: {=_xlfn._xlws.SORT(N1:O20,2,-1)} -> IEEE | R1: 14 | T1: =Q1 -> IEEE | U1: =R1 -> 14
A2: Scopus | B2: Neural Computing and Applications | C2: Springer Nature | E2: IEEE Xplore | F2: =COUNTIF(_xlfn.ANCHORARRAY($A$1),E2) -> 3 | H2: SBC OpenLib | I2: 7 | K2: Neural Computing and Applications | L2: =COUNTIF(_xlfn.ANCHORARRAY($B$1),K2) -> 1 | N2: Springer Nature | O2: =COUNTIF(_xlfn.ANCHORARRAY($C$1),N2) -> 5 | Q2: SBC | R2: 7 | T2: =Q2 -> SBC | U2: =R2 -> 7
A3: Scopus | B3: The International Arab Journal of Information Technology (IAJIT) | C3: Zarqa University | E3: ACM Digital Library | F3: =COUNTIF(_xlfn.ANCHORARRAY($A$1),E3) -> 1 | H3: IEEE Xplore | I3: 3 | K3: The International Arab Journal of Information Technology (IAJIT) | L3: =COUNTIF(_xlfn.ANCHORARRAY($B$1),K3) -> 1 | N3: Zarqa University | O3: =COUNTIF(_xlfn.ANCHORARRAY($C$1),N3) -> 1 | Q3: Springer Nature | R3: 5 | T3: =Q3 -> Springer Nature | U3: =R3 -> 5
A4: Scopus | B4: SN Computer Science | C4: Springer Nature | E4: Web of Science | F4: =COUNTIF(_xlfn.ANCHORARRAY($A$1),E4) -> 1 | H4: ACM Digital Library | I4: 1 | K4: SN Computer Science | L4: =COUNTIF(_xlfn.ANCHORARRAY($B$1),K4) -> 1 | N4: Zenodo | O4: =COUNTIF(_xlfn.ANCHORARRAY($C$1),N4) -> 1 | Q4: MDPI | R4: 5 | T4: =Q4 -> MDPI | U4: =R4 -> 5
A5: Scopus | B5: Discover Artificial Intelligence | C5: Springer Nature | E5: Springer Link | F5: =COUNTIF(_xlfn.ANCHORARRAY($A$1),E5) -> 1 | H5: Web of Science | I5: 1 | K5: Discover Artificial Intelligence | L5: =COUNTIF(_xlfn.ANCHORARRAY($B$1),K5) -> 1 | N5: Inderscience Publishers | O5: =COUNTIF(_xlfn.ANCHORARRAY($C$1),N5) -> 1 | Q5: Elsevier | R5: 4 | T5: =Q5 -> Elsevier | U5: =R5 -> 4
A6: Scopus | B6: Journal of Educational Data Mining | C6: Zenodo | E6: SBC OpenLib | F6: =COUNTIF(_xlfn.ANCHORARRAY($A$1),E6) -> 7 | H6: Springer Link | I6: 1 | K6: Journal of Educational Data Mining | L6: =COUNTIF(_xlfn.ANCHORARRAY($B$1),K6) -> 1 | N6: IEEE | O6: =COUNTIF(_xlfn.ANCHORARRAY($C$1),N6) -> 14 | Q6: ACM | R6: 3 | T6: =Q6 -> ACM | U6: =R6 -> 3
A7: Scopus | B7: International Journal of Information and Communication Technology | C7: Inderscience Publishers | K7: International Journal of Information and Communication Technology | L7: =COUNTIF(_xlfn.ANCHORARRAY($B$1),K7) -> 1 | N7: MDPI | O7: =COUNTIF(_xlfn.ANCHORARRAY($C$1),N7) -> 5 | Q7: PeerJ | R7: 2 | T7: =Q7 -> PeerJ | U7: =R7 -> 2
A8: Scopus | B8: 2024 International Conference on Electronics, Computing, Communication and Control Technology (ICECCC) | C8: IEEE | K8: 2024 International Conference on Electronics, Computing, Communication and Control Technology (ICECCC) | L8: =COUNTIF(_xlfn.ANCHORARRAY($B$1),K8) -> 1 | N8: Elsevier | O8: =COUNTIF(_xlfn.ANCHORARRAY($C$1),N8) -> 4 | Q8: University of Latvia | R8: 1 | T8: Others | U8: =SUM(R8:R20) -> 13
A9: Scopus | B9: IEEE Access | C9: IEEE | K9: IEEE Access | L9: =COUNTIF(_xlfn.ANCHORARRAY($B$1),K9) -> 2 | N9: PeerJ | O9: =COUNTIF(_xlfn.ANCHORARRAY($C$1),N9) -> 2 | Q9: Zarqa University | R9: 1
A10: Scopus | B10: electronics | C10: MDPI | K10: electronics | L10: =COUNTIF(_xlfn.ANCHORARRAY($B$1),K10) -> 1 | N10: Hindawi | O10: =COUNTIF(_xlfn.ANCHORARRAY($C$1),N10) -> 1 | Q10: Zenodo | R10: 1
A11: Scopus | B11: Computers and Electrical Engineering | C11: Elsevier | K11: Computers and Electrical Engineering | L11: =COUNTIF(_xlfn.ANCHORARRAY($B$1),K11) -> 1 | N11: SPIE | O11: =COUNTIF(_xlfn.ANCHORARRAY($C$1),N11) -> 1 | Q11: Inderscience Publishers | R11: 1
A12: Scopus | B12: Journal of Ambient Intelligence and Humanized Computing | C12: Springer Nature | K12: Journal of Ambient Intelligence and Humanized Computing | L12: =COUNTIF(_xlfn.ANCHORARRAY($B$1),K12) -> 1 | N12: Bright | O12: =COUNTIF(_xlfn.ANCHORARRAY($C$1),N12) -> 1 | Q12: Hindawi | R12: 1
A13: Scopus | B13: Mathematics | C13: MDPI | K13: Mathematics | L13: =COUNTIF(_xlfn.ANCHORARRAY($B$1),K13) -> 1 | N13: International Educational Data Mining Society | O13: =COUNTIF(_xlfn.ANCHORARRAY($C$1),N13) -> 1 | Q13: SPIE | R13: 1
A14: Scopus | B14: IEEE Transactions on Big Data | C14: IEEE | K14: IEEE Transactions on Big Data | L14: =COUNTIF(_xlfn.ANCHORARRAY($B$1),K14) -> 1 | N14: IGI Global Scientific Publishing | O14: =COUNTIF(_xlfn.ANCHORARRAY($C$1),N14) -> 1 | Q14: Bright | R14: 1
A15: Scopus | B15: PeerJ Computer Science | C15: PeerJ | K15: PeerJ Computer Science | L15: =COUNTIF(_xlfn.ANCHORARRAY($B$1),K15) -> 2 | N15: Science Publications | O15: =COUNTIF(_xlfn.ANCHORARRAY($C$1),N15) -> 1 | Q15: International Educational Data Mining Society | R15: 1
A16: Scopus | B16: IEEE Access | C16: IEEE | K16: Mobile Information Systems | L16: =COUNTIF(_xlfn.ANCHORARRAY($B$1),K16) -> 1 | N16: SciEngine | O16: =COUNTIF(_xlfn.ANCHORARRAY($C$1),N16) -> 1 | Q16: IGI Global Scientific Publishing | R16: 1
A17: Scopus | B17: Mobile Information Systems | C17: Hindawi | K17: International Conference on Algorithms, Image Processing, and Deep Learning (AIPDL 2025) | L17: =COUNTIF(_xlfn.ANCHORARRAY($B$1),K17) -> 1 | N17: ACM | O17: =COUNTIF(_xlfn.ANCHORARRAY($C$1),N17) -> 3 | Q17: Science Publications | R17: 1
A18: Scopus | B18: International Conference on Algorithms, Image Processing, and Deep Learning (AIPDL 2025) | C18: SPIE | K18: Applied Sciences | L18: =COUNTIF(_xlfn.ANCHORARRAY($B$1),K18) -> 2 | N18: Emeral Publishing Limited | O18: =COUNTIF(_xlfn.ANCHORARRAY($C$1),N18) -> 1 | Q18: SciEngine | R18: 1
A19: Scopus | B19: Applied Sciences | C19: MDPI | K19: 2025 IEEE Frontiers in Education Conference (FIE) | L19: =COUNTIF(_xlfn.ANCHORARRAY($B$1),K19) -> 1 | N19: SBC | O19: =COUNTIF(_xlfn.ANCHORARRAY($C$1),N19) -> 7 | Q19: Emeral Publishing Limited | R19: 1
A20: Scopus | B20: PeerJ Computer Science | C20: PeerJ | K20: Journal of Applied Sciences (JADS) | L20: =COUNTIF(_xlfn.ANCHORARRAY($B$1),K20) -> 1 | N20: Noves Ricerca | O20: =COUNTIF(_xlfn.ANCHORARRAY($C$1),N20) -> 1 | Q20: Noves Ricerca | R20: 1
A21: Scopus | B21: 2025 IEEE Frontiers in Education Conference (FIE) | C21: IEEE | K21: 16th International Conference on Educational Data Mining | L21: =COUNTIF(_xlfn.ANCHORARRAY($B$1),K21) -> 1
A22: Scopus | B22: Journal of Applied Sciences (JADS) | C22: Bright | K22: International Journal of e-Collaboration | L22: =COUNTIF(_xlfn.ANCHORARRAY($B$1),K22) -> 1
A23: Scopus | B23: 16th International Conference on Educational Data Mining | C23: International Educational Data Mining Society | K23: 2022 IEEE 4th International Conference on Cognitive Machine Intelligence (CogMI) | L23: =COUNTIF(_xlfn.ANCHORARRAY($B$1),K23) -> 1
A24: Scopus | B24: International Journal of e-Collaboration | C24: IGI Global Scientific Publishing | K24: Journal of Computer Science | L24: =COUNTIF(_xlfn.ANCHORARRAY($B$1),K24) -> 1
A25: Scopus | B25: 2022 IEEE 4th International Conference on Cognitive Machine Intelligence (CogMI) | C25: IEEE | K25: Computers and Education: Artificial Intelligence | L25: =COUNTIF(_xlfn.ANCHORARRAY($B$1),K25) -> 2
A26: Scopus | B26: Journal of Computer Science | C26: Science Publications | K26: Data Intelligence | L26: =COUNTIF(_xlfn.ANCHORARRAY($B$1),K26) -> 1
A27: Scopus | B27: Applied Sciences | C27: MDPI | K27: 2025 International Conference on Data Science, Agents & Artificial Intelligence (ICDSAAI) | L27: =COUNTIF(_xlfn.ANCHORARRAY($B$1),K27) -> 1
A28: Scopus | B28: Computers and Education: Artificial Intelligence | C28: Elsevier | K28: Expert Systems With Applications | L28: =COUNTIF(_xlfn.ANCHORARRAY($B$1),K28) -> 1
A29: Scopus | B29: Data Intelligence | C29: SciEngine | K29: Data | L29: =COUNTIF(_xlfn.ANCHORARRAY($B$1),K29) -> 1
A30: IEEE Xplore | B30: 2025 International Conference on Data Science, Agents & Artificial Intelligence (ICDSAAI) | C30: IEEE | K30: ISAIE '24: Proceedings of the 2024 International Symposium on Artificial Intelligence for Education | L30: =COUNTIF(_xlfn.ANCHORARRAY($B$1),K30) -> 1
A31: Scopus | B31: Computers and Education: Artificial Intelligence | C31: Elsevier | K31: UMAP '25: Proceedings of the 33rd ACM Conference on User Modeling, Adaptation and Personalization | L31: =COUNTIF(_xlfn.ANCHORARRAY($B$1),K31) -> 1
A32: Scopus | B32: Expert Systems With Applications | C32: Elsevier | K32: 2025 3rd International Conference on Artificial Intelligence and Machine Learning Applications Theme: Healthcare and Internet of Things (AIMLA) | L32: =COUNTIF(_xlfn.ANCHORARRAY($B$1),K32) -> 1
... A48: SBC OpenLib | B48: 2024: Anais do XXXII Workshop sobre Educação em Computação | C48: SBC | K48: 2026 IEEE 2nd International Conference on Electronics, Energy Systems and Power Engineering (EESPE) | L48: =COUNTIF(_xlfn.ANCHORARRAY($B$1),K48) -> 1
A49: SBC OpenLib | B49: 2026: Anais da XXI Escola Regional de Banco de Dados | C49: SBC
A50: IEEE Xplore | B50: 2026 4th International Conference on Sustainable Computing and Smart Systems (ICSCSS) | C50: IEEE
A51: Scopus | B51: 2026 International Conference on Intelligent Engineering and Next-Gen Healthcare Systems (IEHNS) | C51: IEEE
A52: Scopus | B52: Journal of Intelligent Decision Making and Information Science | C52: Noves Ricerca
A53: Scopus | B53: 2026 IEEE 2nd International Conference on Electronics, Energy Systems and Power Engineering (EESPE) | C53: IEEE

Sheet Articles per Author's Country
A1: {=_xlfn.UNIQUE(Articles[Country of the first author’s institution])} -> Latvia | B1: =COUNTIF(Articles[Country of the first author’s institution],A1) -> 1 | D1: {=_xlfn._xlws.SORT(A1:B18,2,-1)} -> China | E1: 15
A2: Pakistan | B2: =COUNTIF(Articles[Country of the first author’s institution],A2) -> 1 | D2: India | E2: 9
A3: China | B3: =COUNTIF(Articles[Country of the first author’s institution],A3) -> 15 | D3: Brazil | E3: 7
A4: Vietnam | B4: =COUNTIF(Articles[Country of the first author’s institution],A4) -> 2 | D4: United States | E4: 5
A5: Germany | B5: =COUNTIF(Articles[Country of the first author’s institution],A5) -> 2 | D5: Vietnam | E5: 2
A6: India | B6: =COUNTIF(Articles[Country of the first author’s institution],A6) -> 9 | D6: Germany | E6: 2
A7: Romania | B7: =COUNTIF(Articles[Country of the first author’s institution],A7) -> 1 | D7: Morocco | E7: 2
A8: Spain | B8: =COUNTIF(Articles[Country of the first author’s institution],A8) -> 1 | D8: Latvia | E8: 1
A9: Serbia | B9: =COUNTIF(Articles[Country of the first author’s institution],A9) -> 1 | D9: Pakistan | E9: 1
A10: Cyprus | B10: =COUNTIF(Articles[Country of the first author’s institution],A10) -> 1 | D10: Romania | E10: 1
A11: Russia | B11: =COUNTIF(Articles[Country of the first author’s institution],A11) -> 1 | D11: Spain | E11: 1
A12: United States | B12: =COUNTIF(Articles[Country of the first author’s institution],A12) -> 5 | D12: Serbia | E12: 1
A13: Indonesia | B13: =COUNTIF(Articles[Country of the first author’s institution],A13) -> 1 | D13: Cyprus | E13: 1
... A18: Australia | B18: =COUNTIF(Articles[Country of the first author’s institution],A18) -> 1 | D18: Australia | E18: 1

Sheet Articles per Student Features
B1: {=TRANSPOSE(_xlfn.UNIQUE(Articles[Teaching environment]))} -> Online | C1: In-person | D1: Hybrid
A2: {=_xlfn._xlws.SORT(_xlfn.UNIQUE(TRIM(_xlfn.TOCOL(_xlfn.TEXTSPLIT(_xlfn.TEXTJOIN(",", TRUE, Articles[Type of student data used for training]), ",")))))} -> Academic records | B2: =COUNTIFS(Articles[[Type of student data used for training]:[Type of student data used for training]], "*" & 'Articles per Student Features'!$A2 & "*", Articles[[Teaching environment]:[Teaching environment]], 'Articles per Student Features'!B$1) -> 13 | C2: =COUNTIFS(Articles[[Type of student data used for training]:[Type of student data used for training]], "*" & 'Articles per Student Features'!$A2 & "*", Articles[[Teaching environment]:[Teaching environment]], 'Articles per Student Features'!C$1) -> 22 | D2: =COUNTIFS(Articles[[Type of student data used for training]:[Type of student data used for training]], "*" & 'Articles per Student Features'!$A2 & "*", Articles[[Teaching environment]:[Teaching environment]], 'Articles per Student Features'!D$1) -> 9
A3: Demographic data | B3: =COUNTIFS(Articles[[Type of student data used for training]:[Type of student data used for training]], "*" & 'Articles per Student Features'!$A3 & "*", Articles[[Teaching environment]:[Teaching environment]], 'Articles per Student Features'!B$1) -> 10 | C3: =COUNTIFS(Articles[[Type of student data used for training]:[Type of student data used for training]], "*" & 'Articles per Student Features'!$A3 & "*", Articles[[Teaching environment]:[Teaching environment]], 'Articles per Student Features'!C$1) -> 16 | D3: =COUNTIFS(Articles[[Type of student data used for training]:[Type of student data used for training]], "*" & 'Articles per Student Features'!$A3 & "*", Articles[[Teaching environment]:[Teaching environment]], 'Articles per Student Features'!D$1) -> 4
A4: Knowledge component | B4: =COUNTIFS(Articles[[Type of student data used for training]:[Type of student data used for training]], "*" & 'Articles per Student Features'!$A4 & "*", Articles[[Teaching environment]:[Teaching environment]], 'Articles per Student Features'!B$1) -> 0 | C4: =COUNTIFS(Articles[[Type of student data used for training]:[Type of student data used for training]], "*" & 'Articles per Student Features'!$A4 & "*", Articles[[Teaching environment]:[Teaching environment]], 'Articles per Student Features'!C$1) -> 1 | D4: =COUNTIFS(Articles[[Type of student data used for training]:[Type of student data used for training]], "*" & 'Articles per Student Features'!$A4 & "*", Articles[[Teaching environment]:[Teaching environment]], 'Articles per Student Features'!D$1) -> 0
A5: Multi-modal data | B5: =COUNTIFS(Articles[[Type of student data used for training]:[Type of student data used for training]], "*" & 'Articles per Student Features'!$A5 & "*", Articles[[Teaching environment]:[Teaching environment]], 'Articles per Student Features'!B$1) -> 1 | C5: =COUNTIFS(Articles[[Type of student data used for training]:[Type of student data used for training]], "*" & 'Articles per Student Features'!$A5 & "*", Articles[[Teaching environment]:[Teaching environment]], 'Articles per Student Features'!C$1) -> 4 | D5: =COUNTIFS(Articles[[Type of student data used for training]:[Type of student data used for training]], "*" & 'Articles per Student Features'!$A5 & "*", Articles[[Teaching environment]:[Teaching environment]], 'Articles per Student Features'!D$1) -> 1
A6: VLE activity log | B6: =COUNTIFS(Articles[[Type of student data used for training]:[Type of student data used for training]], "*" & 'Articles per Student Features'!$A6 & "*", Articles[[Teaching environment]:[Teaching environment]], 'Articles per Student Features'!B$1) -> 16 | C6: =COUNTIFS(Articles[[Type of student data used for training]:[Type of student data used for training]], "*" & 'Articles per Student Features'!$A6 & "*", Articles[[Teaching environment]:[Teaching environment]], 'Articles per Student Features'!C$1) -> 0 | D6: =COUNTIFS(Articles[[Type of student data used for training]:[Type of student data used for training]], "*" & 'Articles per Student Features'!$A6 & "*", Articles[[Teaching environment]:[Teaching environment]], 'Articles per Student Features'!D$1) -> 4

Sheet Articles per Architecture
B1: {=TRANSPOSE(_xlfn.UNIQUE(Articles[Teaching environment]))} -> Online | C1: In-person | D1: Hybrid
A2: {=_xlfn.UNIQUE(Articles[Machine learning architecture])} -> Deep learning | B2: =COUNTIFS(Articles[[Machine learning architecture]:[Machine learning architecture]],$A2,Articles[[Teaching environment]:[Teaching environment]],B$1) -> 10 | C2: =COUNTIFS(Articles[[Machine learning architecture]:[Machine learning architecture]],$A2,Articles[[Teaching environment]:[Teaching environment]],C$1) -> 5 | D2: =COUNTIFS(Articles[[Machine learning architecture]:[Machine learning architecture]],$A2,Articles[[Teaching environment]:[Teaching environment]],D$1) -> 1 | F2: =B2/SUM(B$2:B$5) -> 0.52631579 | G2: =C2/SUM(C$2:C$5) -> 0.20833333 | H2: =D2/SUM(D$2:D$5) -> 0.1
A3: Ensemble learning | B3: =COUNTIFS(Articles[[Machine learning architecture]:[Machine learning architecture]],$A3,Articles[[Teaching environment]:[Teaching environment]],B$1) -> 6 | C3: =COUNTIFS(Articles[[Machine learning architecture]:[Machine learning architecture]],$A3,Articles[[Teaching environment]:[Teaching environment]],C$1) -> 9 | D3: =COUNTIFS(Articles[[Machine learning architecture]:[Machine learning architecture]],$A3,Articles[[Teaching environment]:[Teaching environment]],D$1) -> 4 | F3: =B3/SUM(B$2:B$5) -> 0.31578947 | G3: =C3/SUM(C$2:C$5) -> 0.375 | H3: =D3/SUM(D$2:D$5) -> 0.4
A4: Reinforcement learning | B4: =COUNTIFS(Articles[[Machine learning architecture]:[Machine learning architecture]],$A4,Articles[[Teaching environment]:[Teaching environment]],B$1) -> 1 | C4: =COUNTIFS(Articles[[Machine learning architecture]:[Machine learning architecture]],$A4,Articles[[Teaching environment]:[Teaching environment]],C$1) -> 2 | D4: =COUNTIFS(Articles[[Machine learning architecture]:[Machine learning architecture]],$A4,Articles[[Teaching environment]:[Teaching environment]],D$1) -> 0 | F4: =B4/SUM(B$2:B$5) -> 0.052631579 | G4: =C4/SUM(C$2:C$5) -> 0.083333333 | H4: =D4/SUM(D$2:D$5) -> 0
A5: Machine learning | B5: =COUNTIFS(Articles[[Machine learning architecture]:[Machine learning architecture]],$A5,Articles[[Teaching environment]:[Teaching environment]],B$1) -> 2 | C5: =COUNTIFS(Articles[[Machine learning architecture]:[Machine learning architecture]],$A5,Articles[[Teaching environment]:[Teaching environment]],C$1) -> 8 | D5: =COUNTIFS(Articles[[Machine learning architecture]:[Machine learning architecture]],$A5,Articles[[Teaching environment]:[Teaching environment]],D$1) -> 5 | F5: =B5/SUM(B$2:B$5) -> 0.10526316 | G5: =C5/SUM(C$2:C$5) -> 0.33333333 | H5: =D5/SUM(D$2:D$5) -> 0.5

Sheet Articles per Limitations
B1: {=TRANSPOSE(_xlfn.UNIQUE(Articles[Teaching environment]))} -> Online | C1: In-person | D1: Hybrid
A2: {=_xlfn._xlws.SORT(_xlfn.UNIQUE(TRIM(_xlfn.TOCOL(_xlfn.TEXTSPLIT(_xlfn.TEXTJOIN(",", TRUE, Articles[ [ Types of reported barriers or limitations] ]), ",")))))} -> Class imbalance | B2: =COUNTIFS(Articles[[ Types of reported barriers or limitations]:[ Types of reported barriers or limitations]], "*" & 'Articles per Limitations'!$A2 & "*", Articles[[Teaching environment]:[Teaching environment]], 'Articles per Limitations'!B$1) -> 6 | C2: =COUNTIFS(Articles[[ Types of reported barriers or limitations]:[ Types of reported barriers or limitations]], "*" & 'Articles per Limitations'!$A2 & "*", Articles[[Teaching environment]:[Teaching environment]], 'Articles per Limitations'!C$1) -> 7 | D2: =COUNTIFS(Articles[[ Types of reported barriers or limitations]:[ Types of reported barriers or limitations]], "*" & 'Articles per Limitations'!$A2 & "*", Articles[[Teaching environment]:[Teaching environment]], 'Articles per Limitations'!D$1) -> 3
A3: Data availability | B3: =COUNTIFS(Articles[[ Types of reported barriers or limitations]:[ Types of reported barriers or limitations]], "*" & 'Articles per Limitations'!$A3 & "*", Articles[[Teaching environment]:[Teaching environment]], 'Articles per Limitations'!B$1) -> 5 | C3: =COUNTIFS(Articles[[ Types of reported barriers or limitations]:[ Types of reported barriers or limitations]], "*" & 'Articles per Limitations'!$A3 & "*", Articles[[Teaching environment]:[Teaching environment]], 'Articles per Limitations'!C$1) -> 5 | D3: =COUNTIFS(Articles[[ Types of reported barriers or limitations]:[ Types of reported barriers or limitations]], "*" & 'Articles per Limitations'!$A3 & "*", Articles[[Teaching environment]:[Teaching environment]], 'Articles per Limitations'!D$1) -> 4
A4: Model generalization | B4: =COUNTIFS(Articles[[ Types of reported barriers or limitations]:[ Types of reported barriers or limitations]], "*" & 'Articles per Limitations'!$A4 & "*", Articles[[Teaching environment]:[Teaching environment]], 'Articles per Limitations'!B$1) -> 9 | C4: =COUNTIFS(Articles[[ Types of reported barriers or limitations]:[ Types of reported barriers or limitations]], "*" & 'Articles per Limitations'!$A4 & "*", Articles[[Teaching environment]:[Teaching environment]], 'Articles per Limitations'!C$1) -> 11 | D4: =COUNTIFS(Articles[[ Types of reported barriers or limitations]:[ Types of reported barriers or limitations]], "*" & 'Articles per Limitations'!$A4 & "*", Articles[[Teaching environment]:[Teaching environment]], 'Articles per Limitations'!D$1) -> 2
A5: Privacy concerns | B5: =COUNTIFS(Articles[[ Types of reported barriers or limitations]:[ Types of reported barriers or limitations]], "*" & 'Articles per Limitations'!$A5 & "*", Articles[[Teaching environment]:[Teaching environment]], 'Articles per Limitations'!B$1) -> 5 | C5: =COUNTIFS(Articles[[ Types of reported barriers or limitations]:[ Types of reported barriers or limitations]], "*" & 'Articles per Limitations'!$A5 & "*", Articles[[Teaching environment]:[Teaching environment]], 'Articles per Limitations'!C$1) -> 3 | D5: =COUNTIFS(Articles[[ Types of reported barriers or limitations]:[ Types of reported barriers or limitations]], "*" & 'Articles per Limitations'!$A5 & "*", Articles[[Teaching environment]:[Teaching environment]], 'Articles per Limitations'!D$1) -> 3
A6: Resource overhead | B6: =COUNTIFS(Articles[[ Types of reported barriers or limitations]:[ Types of reported barriers or limitations]], "*" & 'Articles per Limitations'!$A6 & "*", Articles[[Teaching environment]:[Teaching environment]], 'Articles per Limitations'!B$1) -> 2 | C6: =COUNTIFS(Articles[[ Types of reported barriers or limitations]:[ Types of reported barriers or limitations]], "*" & 'Articles per Limitations'!$A6 & "*", Articles[[Teaching environment]:[Teaching environment]], 'Articles per Limitations'!C$1) -> 3 | D6: =COUNTIFS(Articles[[ Types of reported barriers or limitations]:[ Types of reported barriers or limitations]], "*" & 'Articles per Limitations'!$A6 & "*", Articles[[Teaching environment]:[Teaching environment]], 'Articles per Limitations'!D$1) -> 2
A7: Result interpretability | B7: =COUNTIFS(Articles[[ Types of reported barriers or limitations]:[ Types of reported barriers or limitations]], "*" & 'Articles per Limitations'!$A7 & "*", Articles[[Teaching environment]:[Teaching environment]], 'Articles per Limitations'!B$1) -> 1 | C7: =COUNTIFS(Articles[[ Types of reported barriers or limitations]:[ Types of reported barriers or limitations]], "*" & 'Articles per Limitations'!$A7 & "*", Articles[[Teaching environment]:[Teaching environment]], 'Articles per Limitations'!C$1) -> 4 | D7: =COUNTIFS(Articles[[ Types of reported barriers or limitations]:[ Types of reported barriers or limitations]], "*" & 'Articles per Limitations'!$A7 & "*", Articles[[Teaching environment]:[Teaching environment]], 'Articles per Limitations'!D$1) -> 0

Sheet Articles
A1: article | B1: DOI (unique identifier) | C1: Author(s) | D1: Publication year | E1: Repository, journal/proceeding, and publisher | F1: Country of the first author’s institution | G1: Main contributions of the study | H1: Sample size (number of students) | I1: Teaching environment | J1: Features collected from monitored students | K1: Type of student data used for training | L1: Prediction models applied | M1: Machine learning architecture | N1: Evaluated models' performance metrics | O1: Results: Technical and/or pedagogical improvements | P1: Reported barriers or limitations | Q1: Types of reported barriers or limitations | R1: Ethical and privacy considerations
A2: Predicting Student Performance on a Novel Moodle Dataset Using GRU Time Series Model | B2: 10.22364/bjmc.2025.13.4.07 | C2: Sneiders, Martins and Urtans, Evalds and Abu Saa, Amjed | D2: 2025 | E2: Scopus, Baltic Journal of Modern Computing, University of Latvia | F2: Latvia | G2: The main contribution of this paper is the dataset provided by the University of Latvia, which comprises over 1.259.411 student activity logs and 20.317 final grade records from a Moodle virtual learning environment across an academic semester. Made publicly available on Kaggle, this dataset was used to train a GRU-based predictive model. | H2: Tables 2 and 3: The dataset contained records for 6.990 students from the University of Latvia. Model validation (testing) used a 20% random sample, while training used the remaining 80%. The model was trained to classify students into 11 grade categories ranging from 0 to 10. The dataset also included a group of students with a grade of -1, representing unrecorded grades. The initial training iteration—using activity logs alone—proved ineffective; thus, the final model was trained on a subset of 216 courses (3,5%) that included assigned final grades. | I2: Online | J2: User activity logs, including logins, chapter access, response submissions, and posted course assessments, along with student final course grades for the semester. | K2: Academic records, VLE activity log | L2: The predictive model applied was based on Gated Recurrent Units (GRU), with the experiment focusing on classifying students into one of 11 grade groups based on their dropout risk. | M2: Deep learning | N2: Accuracy. | O2: The model achieved an accuracy of 83% when integrating intermediate grades (Figure 1), compared to 80% when using only user activity data (Figure 2). | P2: The authors report that the dataset contained data from only a single academic semester and suggest integrating additional semesters in future studies. Furthermore, the majority of activity logs were generated by less than 5% of users and were concentrated in just a few courses, primarily those related to information technology. The authors also highlight a severe class imbalance in the dataset, where 76,1% of the grades fall within the 8–10 range, whereas only 4,6% represent lower grades (0–3). Consequently, they recommend exploring additional error and calibration metrics in future research. | Q2: Class imbalance, Model generalization, Privacy concerns | R2: The dataset was obtained under a non-disclosure agreement with the university. For future research, the authors highlight privacy-preserving collaborative approaches—such as federated learning—to avoid exposing raw data while potentially enhancing model generalization.
A3: Introducing the Hyperdynamic Adaptive Learning Fusion (HALF) model for superior predictive analytics in E-learning | B3: 10.1007/s00521-025-11018-7 | C3: Islam, Umar and Alali, Ibrahim Khalil and Alotaibi, Shoayee Dlaim and Alzaid, Zaid and Shah, Babar and Ali, Ijaz and Moreira, Fernando | D3: March 13, 2025 | E3: Scopus, Neural Computing and Applications, Springer Nature | F3: Pakistan | G3: The development of the Hyperdynamic Adaptive Learning Fusion (HALF) leverages a fusion strategy that integrates a base model, focused on capturing general behavior patterns, and an adaptive model, capable of identifying contextual nuances and temporal variables. This architecture allows for greater efficiency despite the heterogeneous and dynamic nature of educational data, incorporating feedback loops for continuous self-adjustment of the learning process of new students in real time. In addition to processing large volumes of programmatic content, the HALF model employs advanced techniques to deeply understand the student's interaction-affect-performance profile. The model actively seeks to mitigate biases to ensure equal opportunities for students of different ethnic backgrounds. Furthermore, it was designed to operate in synergy with current learning management systems, seeking to maximize accessibility and usability for instructors. | H3: The dataset was extracted from the Open University Virtual Learning Environment and contains approximately 500.000 records of roughly 170.000 students across multiple courses and academic years. The features were chosen based on their relevance for predicting student outcomes, given that previous research demonstrated that factors such as demographic and behavioral data are intimately related to performance. Finally, the dataset was partitioned into training, validation, and test sets using an 80/10/10 ratio. | I3: Online | J3: Table 1: The variables include demographic data—location, age, disabilities, educational level, and gender—as well as performance indicators: assignment grades and virtual learning environment interaction metrics. The preprocessing involved imputing missing numerical values using the mean or median, using the mode for categorical variables, removing records with excessive missing values, and normalizing continuous variables (performance indicators). For categorical variables, one-hot encoding was employed to ensure that the model processes this information efficiently, without introducing artificial hierarchies or biases. Conversely, continuous variables were handled using interquartile range (IQR) analysis for outlier identification and removal, preventing extreme values from distorting system performance and learning. | K3: Academic records, Demographic data, VLE activity log | L3: The HALF model is based on the combination of two models via an optimized fusion parameter. First, a base model is trained on the entire dataset to learn general patterns—employing the Bagging technique, which consists of training multiple instances of the model on random partitions of the dataset to reduce variance, making predictions more stable and resistant to noise. Second, an adaptive model is designed to identify contextual and time-sensitive patterns—capturing rapid changes in engagement that static models overlook—by employing the Boosting technique, which trains the model sequentially to reduce errors of previous iterations, focusing on hard-to-predict cases and reducing overall system bias. To mitigate overfitting, L2 regularization and dropout techniques were employed, and training was stopped early when performance stagnated. | M3: Ensemble learning | N3: Accuracy, Precision, Recall, and F1-Score. The proposed model was benchmarked against conventional models (e.g., SVM and KNN), as well as standalone architectures of only-bagging and only-boosting. | O3: Table 6: The model demonstrated superior results when compared to the baseline models: 87% accuracy, 85% precision, 84% recall, and an 84% F1-Score. On the other hand, the HALF model required a higher training time (215 seconds). Table 4: The model performance decreased—and training time increased—as the dataset size grew. Furthermore, the proposed model presented a superior performance in the in-person environment compared to the online environment (Table 5). Results also indicated that frequent student interaction with the VLE platform is strongly positively correlated with higher assessment scores. | P3: The continuous tuning and training process increased the system's computational complexity. Bagging and Boosting techniques require intensive computational resources—thus the author's alert to potential latency impacts and computational overhead during real-time operations, suggesting that future research explore distributed computing and parallel processing. | Q3: Resource overhead, Result interpretability | R3: Despite not discussing the informed consent for the dataset employed, the authors addressed interpretability, bias reduction, and equity in the proposed model.
A4: Cognitive-Fuzzy Learning System-Based University English Smart Classroom Teaching Design and Application | B4: 10.34028/iajit/23/4/13 | C4: Lai, Ningyi | D4: December 8, 2025 | E4: Scopus, The International Arab Journal of Information Technology (IAJIT), Zarqa University | F4: China | G4: Propose the Cognitive-Fuzzy Adaptive Learning Algorithm (CFALA), a novel hybrid architecture combining cognitive psychology (ACT-R) with fuzzy logic (ANFIS) and reinforcement learning (Q-learning) for personalized, real-time classroom adaptation. Designed a comprehensive smart classroom framework containing 5 interconnected modules: Data Collection, Cognitive Processing, Fuzzy Inference Engine, Adaptive Strategy Generator, and Smart Classroom Interface. Demonstrated empirical superiority of CFALA over three state-of-the-art alternative frameworks across student engagement, learning outcomes, responsiveness, and feedback accuracy. | H4: Table 2: 500 students, 20 classes, and 25 staff monitored over 1 academic semester (16 weeks). | I4: In-person | J4: Student Interactions (Real-Time): touchscreens, keyboards, voice, classroom participation, online activity, peer collaborations. Performance Metrics (Daily/Weekly): quizzes, assignments, participation, grades, language proficiency tests. Learning Patterns (Continuous): task logs, resource access, time spent on activities, preferred learning resources, learning speed, and intensity. Environmental Data (Real-Time): IoT sensors monitoring classroom temperature, noise levels, lighting, and time of day. Student Demographics: age range, language backgrounds, and prior English proficiency levels. | K4: Academic records, Demographic data, Multi-modal data | L4: ACT-R (Adaptive Control of Thought-Rational): Cognitive architecture modeling procedural memory, declarative memory, goal buffer, and perceptual-motor modules. ANFIS (Adaptive Neuro-Fuzzy Inference System): Integrates neural networks with fuzzy logic to handle data ambiguity and uncertainties. Computes rule firing strength and performs defuzzification via the Centroid Method. Q-Learning Algorithm: Reinforcement learning for iterative teaching strategy optimization. | M4: Reinforcement learning | N4: Student Engagement Score; Learning Outcome Improvement Rate (%); Time to Skill Mastery; User Satisfaction Score; System Responsiveness: Adaptation Speed, Adaptation Accuracy, and Real-time Feedback Delay; System Scalability: Max users, latency, adaptation accuracy, and resource utilization; Real-Time Feedback Accuracy (%). | O4: Table 5: Real-Time Feedback Accuracy: CFALA achieved 95,43%, significantly outperforming CFBLS (87,49%), ANFLM (83,28%), and DAA-UC (79,23%). Learning Outcome Improvement: CFALA consistently achieved the highest improvement rates (~90% to over 100%) across vocabulary, grammar, reading, writing, and overall English compared to baselines. Table 3: System Responsiveness: Adaptation speed was <1 second with 92% adaptation accuracy and immediate real-time feedback (compared to 1,5–3 seconds latency in baseline systems). Table 4: Scalability: Handled 500+ students/class with <1 second latency and optimized resource utilization of <80% (Excellent rating). User Satisfaction: Consistently highest stacked satisfaction ratings across ease of use, perceived effectiveness, learning support, feedback quality, and overall satisfaction. | P4: Data Stream Instability: Heavy reliance on the continuous stability and precision of high-speed, real-time data streams. Manual Rules Setup: Scaling is technically constrained due to the high subject-matter expertise required to manually set up, tune, and refine the fuzzy logic rule base. Generalizability Limits: Currently optimized only for ESL/EFL contexts; broadening to STEM or other areas requires developing domain-specific cognitive and fuzzy models. | Q4: Model generalization, Privacy concerns, Resource overhead, Result interpretability | R4: Data Privacy: Massive real-time data extraction of student behavior, interactions, and biometric indicators presents data privacy risks. Algorithmic Bias: Potential for feedback bias within the adaptive decision-making and reward structures. Lack of Transparency: The "black box" nature of combining complex neural networks (ANFIS) and cognitive architectures raises concerns regarding the transparency of pedagogical decisions.
A5: A Hybrid Approach Using Decision Tree and Multiple Linear Regression for Predicting Students’ Performance Based on Learning Progress and Behavior | B5: 10.1007/s42979-022-01251-5 | C5: Dang, Tran Khanh and Nguyen, Huu Huong Xuan | D5: July 25, 2022 | E5: Scopus, SN Computer Science, Springer Nature | F5: Vietnam | G5: A hybrid approach combining decision trees for qualitative classification of academic performance with multiple linear regression to predict final GPA. | H5: The dataset comprises 326 student records, featuring 40 variables from a higher education institution in the Sultanate of Oman. The data was collected from three primary sources: a Student Information System (SIS), a Learning Management System (LMS)—Moodle—and a video interaction platform (eDity). It covers the period from Spring 2017 to Spring 2021. | I5: Hybrid | J5: The variables include coursework grades for assignments 1 and 2, final exam scores, and indicators for whether a student has failed two or more modules, as well as the failure rate in a specific module. They also track the total number of module attempts, enrollment in the student success center due to academic deficiencies, probation status based on delayed modules, and registration in multiple modules during the current semester. Additionally, the dataset records whether a student studies remotely, their progression rate along the degree plan, and their level of online activity both on and off campus. Video engagement metrics capture play counts, pause frequencies, video likes, and the frequency of replaying specific video segments. Finally, it accounts for any history of academic integrity violations across modules. | K5: Academic records, VLE activity log | L5: Decision Tree for qualitative classification and Multiple Linear Regression for grade prediction. | M5: Machine learning | N5: The performance of the Decision Tree model was evaluated using a Confusion Matrix, Accuracy, Precision, and Recall, while Multiple Linear Regression was assessed using R-Squared, Correlation Coefficient (CC), Mean Absolute Error (MAE), Root Mean Squared Error (RMSE), Relative Absolute Error (RAE), and Root Relative Squared Error (RRSE). | O5: For the Decision Tree model (Table 6), the overall accuracy was 0,472. Class-level precision values were 0,66 for Excellent, 0,528 for Adequate, and 0,17 for Fair, whereas recall values reached 0,631 for Adequate, 0,419 for Good, and 0,326 for Fair. For Multiple Linear Regression (Table 7), the model achieved an R-Squared of 0,316 and a correlation coefficient of 0,5263, with error metrics of MAE = 0,4119, RMSE = 0,5191, RAE = 83,16%, and RRSE = 85,03%. | P5: The authors acknowledged that the accuracy of the proposed model remains low compared to previous studies, a limitation they intend to address in future work. Specifically, the authors noted that using only 17 features resulted in an overly simplistic decision tree. To overcome this, future research should explore alternative classification methods alongside a broader set of evaluation metrics, moving beyond the sole reliance on accuracy. | Q5: Data availability | R5: The dataset included the applicant name field, which suggests that the information was not anonymized.
A6: Research on the refinement of college student education management based on artificial intelligence | B6: 10.1007/s44163-025-00651-9 | C6: Lai, Qiujia | D6: December 12, 2025 | E6: Scopus, Discover Artificial Intelligence, Springer Nature | F6: China | G6: The proposed hybrid model, AGTO-ResRNN, was designed to predict student performance and risk. AGTO was employed for efficient parameter optimization, enhancing convergence and generalization, while ResRNN captured complex sequential patterns from students' behavioral and academic records through residual recurrent learning. This framework enables accurate risk prediction, performance evaluation, and personalized support in academic management using minimal labeled data. | H6: The dataset comprised 1.200 anonymized student records, each featuring 15 attributes, obtained from the Kaggle platform. | I6: Online | J6: Figure 3: The dataset includes students' academic outcomes and behavioral patterns, along with demographic information, such as age, GPA, course load, average grade in curricular components, attendance rate, login count, average session duration, assignment submission rate, forum participation, and the count of educational videos watched. Preprocessing involved Min-Max normalization (Section 4.2) of features to a 0–1 scale, as well as Principal Component Analysis (PCA) (Section 4.3) to extract features with higher correlation to academic performance. The objective of this technique (PCA) was to reduce the dimensionality of complex data and identify the variables with the greatest influence on academic performance. | K6: Academic records, Demographic data, VLE activity log | L6: The AGTO-ResRNN model integrated the AGTO optimizer—inspired by the social dynamics and intelligent group behaviors of gorillas—with the ResRNN neural network. AGTO simulated the complex interactions of these primates, such as migrating to new locations (exploration), following the silverback leader, or competing for females (exploitation), to fine-tune hyperparameters and feature weights, thereby ensuring greater stability and convergence for the system. ResRNN, which incorporates residual error into an RNN layer, was responsible for capturing sequential patterns and long-term dependencies in student behavior and academic performance. By utilizing residual connections that adopted the direct hidden state as a reference, the model mitigated the vanishing gradient problem, enabling deep temporal analysis. | M6: Deep learning | N6: The evaluated metrics were Mean Absolute Error (MAE), Root Mean Square Error (RMSE), Accuracy, Precision, Recall, and F1-Score. (Section 5.5) The MAE and RMSE metrics were compared against the conventional EMD-PSO-SVM model, whereas Accuracy, Precision, Recall, and F1-Score were compared against the CNN-GRU model. | O6: The model achieved a MAE of 0,116, RMSE of 0,183, Accuracy of 98,50%, Precision of 96,54%, Recall of 95,42%, and an F1-Score of 96,00%. Consequently, the proposed model outperformed the baseline models across all evaluated metrics. Furthermore, AGTO-ResRNN was deemed more interpretable and efficient than CNN-GRU and EMD-PSO-SVM due to its lower computational resource requirements. | P6: The authors acknowledged the limitation that the dataset used was tied to a single institution. For future research, they proposed validating the model across datasets from multiple institutions. | Q6: Model generalization | R6: In Section 4.1, "Data Collection", the authors explicitly stated that the collected data were anonymized.
A7: Investigating Demographic Features and their Connection to Performance, Predictions, and Fairness in EDM Models | B7: 10.5281/zenodo.14503515 | C7: Cohausz, Lea and Tschalzev, Andrej and Bartelt, Christian and Stuckenschmidt, Heiner | D7: December 16, 2024 | E7: Scopus, Journal of Educational Data Mining, Zenodo | F7: Germany | G7: This study builds upon the work of Cohausz et al., Investigating the Importance of Demographic Features for EDM-Predictions (2023). Specifically, this follow-up study uses the demographic parity metric to evaluate the impact of demographic features on algorithmic bias. | H7: Consistent with the previous study (Cohausz et al., 2023). | I7: Hybrid | J7: Consistent with the previous study (Cohausz et al., 2023). | K7: Academic records, Demographic data | L7: Consistent with the previous study (Cohausz et al., 2023). | M7: Ensemble learning | N7: Consistent with the previous study (Cohausz et al., 2023). | O7: The central conclusion of the article regarding the analysis of Demographic Parity (DP) is that simply removing demographic features from models—a strategy known as "fairness through unawareness"—does not guarantee the elimination of bias and generally does not substantially alter equity levels measured by this metric. | P7: Consistent with the previous study (Cohausz et al., 2023). | Q7: Privacy concerns | R7: Consistent with the previous study (Cohausz et al., 2023).
A8: Assessment of civic education in universities from a multidimensional perspective: the Integration of OBE and CIPP models | B8: 10.1504/IJICT.2024.143413 | C8: Zhu, Yimin | D8: December 18, 2024 | E8: Scopus, International Journal of Information and Communication Technology, Inderscience Publishers | F8: China | G8: The authors propose an intelligent, multidimensional validation framework based on big data and machine learning that combines the theoretical models of Outcome-Based Education (OBE) and Context, Input, Process, and Product (CIPP). To evaluate civic education (ideological and political) in higher education, the framework integrates predictive machine learning models (Random Forest, SVM, LSTM, and GBM), a meta-model (Logistic Regression) derived from stacking the individual models, and a multimodal data fusion approach. | H8: The study utilized four data sources: 1.000 online learning records, 1.000 survey responses, 5.000 social media comments, and 1.000 teacher evaluation records. Eighty percent of the data was used for training, while the remaining 20% was used for evaluation. | I8: Online | J8: The variables are specified in Table 1 and were grounded in the CIPP model, comprising: Context (student demographics, learning environment resources, and sociocultural factors); Input (quality of instructional materials, faculty resources, and teaching competencies); Process (student actions and instructional activities tracked through learning logs and participation); and Product (final outcomes, such as ideological growth and learning achievement). Within this framework, CIPP provides the raw data and contextual foundation, whereas OBE establishes the success metrics for validating the objectives. | K8: Academic records, Demographic data, VLE activity log | L8: The framework incorporates Random Forest, SVM, LSTM, and GBM models, alongside two meta-models based on weighted and cascaded fusion of the individual model outputs. The proposed framework is grounded in two theoretical models. First, OBE establishes goals and measures achievements through quantitative metrics. The overall score is calculated as the sum of the goals weighted by their respective coefficients, which are determined via correlation analysis and technical expertise. Furthermore, the implementation of the OBE model enables the assessment of learning trends using linear regression on monitored learning progress over time. Second, CIPP structures the data dimensions: context analysis examines student perspectives and the learning environment; input evaluation assesses course material resources and teaching tools; process evaluation tracks student actions and instructional activities; and product evaluation measures student learning outcomes and ideological | M8: Ensemble learning | N8: Model performance was evaluated using Accuracy, Precision, Recall, and F1-Score. Both the standalone machine learning models and the meta-models were assessed, and their results were systematically compared. | O8: The evaluation results for the machine learning techniques are presented in Figure 3. Experimental findings demonstrate that the LSTM model achieved the highest accuracy and F1-score, excelling in the processing of complex sequential data. SVM and GBM also performed well, whereas Random Forest yielded the lowest performance. Finally, the authors maximized evaluation performance by leveraging the complementary strengths of the various machine learning models through a fusion experiment incorporating both weighted and cascaded approaches. The results indicate that the cascaded fusion meta-model achieved superior performance across all evaluated metrics, enabling significantly more comprehensive and reliable decision support than either traditional methods or individual standalone models. | P8: The authors acknowledge that the dataset was collected from a single institution. For future research, they suggest expanding the dataset with data gathered from additional institutions, as well as evaluating alternative machine learning models. | Q8: Model generalization | R8: The authors did not address any ethical or privacy implications.
A9: Predicting Student Dropout Rates in Massive Open Online Courses Using an Attention-Based GCNN Model | B9: 10.1109/ICECCC61767.2024.10593955 | C9: Balachandar, S. and Mann, Shikha and Thangam, A. and Dubey, Vivek Ravishankar and Bindu, V. and Nishant, Neerav | D9: Date of Conference: 02-03 May 2024; Date Added to IEEE Xplore: 23 July 2024 | E9: Scopus, 2024 International Conference on Electronics, Computing, Communication and Control Technology (ICECCC), IEEE | F9: India | G9: This study evaluates the performance of the Attention-Based Graph Convolutional Neural Network (A-GCNN) in predicting student dropout in higher education, with a focus on Massive Open Online Courses (MOOCs). | H9: Data were extracted from a dataset provided by a public online university in the United States, although the sample size was not specified. Appropriate preprocessing steps were performed, including the removal of tuples with missing critical values and the identification of significant features (or variables) based on their positive or negative impact on model performance during training, specifically through permutation testing with random weights. | I9: Online | J9: Section 3.2: Gender, prior academic performance, and engagement in classroom activities, including assignments, quizzes, and presentations. | K9: Academic records, Demographic data, VLE activity log | L9: Attention-Based Graph Convolutional Neural Network (A-GCNN). | M9: Deep learning | N9: Precision, recall, F1-score, and accuracy metrics were evaluated. | O9: Table 1: Performance comparison between the proposed model (A-GCNN) and baseline models (GCNN and A-CNN). The proposed A-GCNN achieved superior performance across all evaluated metrics: 96,6% Precision, 92,3% Recall, 98,7% F1-score, and 97,2% Accuracy. | P9: The authors report limitations regarding the available data, explaining the removal of tuples with data from students who dropped out of the course before completing two semesters. In this context, predicting this group of students represents a critical methodological gap for the study in question. | Q9: Class imbalance, Data availability | R9: The authors do not discuss ethical and privacy issues, nor do they address the informed consent of the students included in the dataset.
A10: IntelliDaM: A Machine Learning-Based Framework for Enhancing the Performance of Decision-Making Processes. A Case Study for Educational Data Mining | B10: 10.1109/ACCESS.2022.3195531 | C10: Czibula, Gabriela and Ciubotariu, George and Maier, Mariana-Ioana and Lisei, Hannelore | D10: August 1, 2022 | E10: Scopus, IEEE Access, IEEE | F10: Romania | G10: This study aims to design a framework based on data mining and machine learning—named IntelliDam—to extract information related to student performance in a real-world case study, as well as to analyze the effectiveness of this structure. It seeks to identify the relevance of data patterns uncovered through unsupervised learning from academic datasets and determine the extent to which these patterns correlate with student achievement. Furthermore, it investigates the importance of the features used in model training and their impact on predictive performance while assessing how performance prediction could be enhanced by incorporating students' results from prerequisite courses as additional training features. | H10: The dataset was collected from the Logic and Functional Programming course, offered in the third semester of the second year of the Mathematics and Computer Science program at Babeş-Bolyai University. The dataset comprised two case studies, totaling 506 instances (Table 3): records collected from the 2018–2019 and 2019–2020 cohorts (in-person), as well as the 2021–2022 cohort (COVID-19 pandemic, thus online). Section 4.A1: The collected data included assignment scores (1–7), practical exam grades (8–9, for Prolog and Lisp, respectively), seminar activity marks (10), attendance across the 7 seminars (11), the final grade in the prerequisite Data Structures and Algorithms course (12), and the final grade in the prerequisite Fundamentals of Programming course (13). For the pandemic period data, only the practical exams (8–9) were not administered. | I10: Hybrid | J10: Section 4.B: Details experiments with five feature configurations (LFP+DSA+FP, LFP+FP, LFP+DSA, LFP, and Relief-based) across two datasets to evaluate the impact of variables on predictive performance. These combinations were applied in supervised and unsupervised models to validate the importance of prerequisites and optimized features via ReliefF. | K10: Academic records | L10: The proposed model uses two learning approaches: in unsupervised learning, the model deals with the issue of student performance analysis by clustering students into performance categories—which can be divided into 7 classes (grades from 4 to 10, where 4 corresponds to failure) or 5 classes (Excellent, Very Good, Good, Satisfactory, and Fail)—using dimensionality reduction methods (t-SNE and UMAP) and the k-means algorithm (Section 3.C). In supervised learning, the authors deal with the problem of student performance prediction, treated here as a regression task. This means that the model estimates a continuous value for the final grade, which is later converted into categories for evaluation purposes. The model implements three main regressors (Section 3.D): Tweedie Regressor, Stochastic Gradient Descent, and Poly (Polynomial Regressor). Finally, the framework was implemented using the scikit and skrebate libraries. | M10: Machine learning | N10: For the supervised learning model, regression metrics (RMSE and NRMSE) and classification metrics (Accuracy, Precision, Recall, and F1-Score) were measured, as described in Section 3.D1. For the unsupervised model, external evaluation metrics were used, which compare the clusters formed by the model with the ground truth labels: Homogeneity, Completeness, and V-measure (Section 3.C1). While classification and clustering metrics indicate better performance when closer to 1, regression metrics (RMSE and NRMSE) indicate higher accuracy when values are lower (closer to 0), representing a smaller error. | O10: The framework's feature analysis used Pearson and Spearman coefficients (Figure 2) to identify the variables with the highest correlation with academic success. For unsupervised learning, the results are visible in Table 6 and Figures 3 and 4, demonstrating that students with similar performance tend to be naturally grouped by the system, revealing consistent learning patterns. In supervised learning (Tables 7 and 8), the polynomial regression model (Poly) presented the best results across all tested scenarios. Predictive performance was significantly optimized by the use of the Relief-based technique and the inclusion of grades from prerequisite courses. Finally, the authors identified that learning patterns were similar in both face-to-face and online environments, although the system faces challenges in accurately predicting the fail class due to external/unpredictable factors. | P10: Circumstances on the exam day, such as stress or poor emotional management, are cited as barriers that machine learning models have difficulty capturing. The system faced significant difficulties in accurately predicting the fail class. | Q10: Class imbalance | R10: The authors did not address the implications of ethical or privacy issues regarding the developed system, nor the informed consent of the students who comprised the dataset.
A11: Design and Implementation of an Intelligent Diagnostic System for Academic Performance Analysis in Medical Education | B11: 10.3390/electronics15132801 | C11: Aucancela, Margarita and González-Briones, Alfonso and Chamoso, Pablo | D11: June 25, 2026 | E11: Scopus, electronics, MDPI | F11: Spain | G11: Dual MLM-RF Framework: Decomposes population-level variance (MLM) while maintaining high-precision individual scoring (RF); Operational XAI: Development of a SHAP-based Priority Index that fuses inferential and predictive weights; Streamlit Deployment: Implementation of a functional prototype featuring Natural Language Clinical Directives for non-technical tutors; Methodological Transparency: Explicit reporting of encoding impacts and MAE parity ratios for algorithmic fairness. | H11: In-person environment: 18.604 longitudinal records; 1.264 unique students. | I11: In-person | J11: Academic: Academic period, curricular level, and course; Sociodemographic: Gender, province of origin, and student age (log-transformed). | K11: Academic records, Demographic data | L11: Random Forest: Optimized with 300 estimators and a depth of 15; selected for capturing non-linear interactions; 3-Level MLM: Primary inferential analyzer used to decompose variance across students and time; Secondary Baselines: XGBoost, Ridge Regression, and Multilayer Perceptron (MLP). | M11: Ensemble learning | N11: MAE, RMSE, R² for regression; Sensitivity, Specificity, AUC-ROC for classification. | O11: Performance metrics for Random Forest (best-performing): Regression: MAE 1,267 ± 0,04; RMSE 1,714 ± 0,05; R² 0,551 ± 0,02; and Classification: Sensitivity 0,532; Specificity 0,940; AUC-ROC 0,903. | P11: Scope: Single-institution context limits immediate external generalization; Behavioral Gap: Absence of LMS behavioral data (clickstream) limits sensitivity (0,532); Data Depth: Lack of section-level or instructor-level identifiers; Validation: Absence of temporal (future-period) cross-validation; Operational: Horizontal scaling costs for real-time SHAP computation in high-concurrent environments. | Q11: Data availability, Model generalization, Resource overhead | R11: The authors implemented an anonymization protocol and quantified fairness through MAE parity ratios. The results indicate equitable performance for 21 of 22 provinces, ensuring the model does not disproportionately penalize structurally vulnerable groups.
A12: MOOC dropout prediction using a fusion deep model based on behaviour features | B12: 10.1016/j.compeleceng.2022.108409 | C12: Zheng, Yafeng and Shao, Zheng and Deng, Mingming and Gao, Zhanghao and Fu, Qian | D12: October 15, 2022 | E12: Scopus, Computers and Electrical Engineering, Elsevier | F12: China | G12: This study proposes a deep fusion model that combines CNN, BiLSTM, and a self-attention mechanism for early dropout prediction in MOOCs. In MOOC environments, course structures are typically organized into weekly learning activities. Within this context, the proposed model maps student behavior into two-dimensional time-series matrices, where columns represent learning behavior rates and rows represent time progression in weeks. Consequently, as the course progresses, the model predicts a student's engagement for the subsequent week based on their historical performance from preceding weeks. A key contribution of this model lies in its use of self-attention to capture global correlations among learning behaviors, thereby enabling the identification of specific actions—such as assignment completion or video consumption—that exert the greatest influence on a student's decision to drop out or persist. | H12: The study utilizes the KDD Cup 2015 dataset from the XuetangX platform, comprising 120.542 enrollment activity records from 79.186 students across 39 courses spanning from October 27, 2013, to August 1, 2014. Each course lasted five weeks. While the raw dataset originally contained activity logs from 11.000 users, behavioral records from 55.045 students were extracted for the training and evaluation of the proposed fusion model. | I12: Online | J12: Tables 1 and 2: The activity logs were categorized by user event type, which includes solving assignments via the browser, accessing course materials via the browser, watching educational videos, closing the course page, participating in forum discussions, navigating to other courses, searching for the course on Wikipedia, accessing course materials via the server, and solving assignments via the server. Each event was mapped to a unique user identifier and a timestamp. | K12: VLE activity log | L12: The proposed approach extracts local features from the dataset using a Convolutional Neural Network (CNN) and applies a max-pooling operation to mitigate redundant features. The fusion model captures inter-feature relationships through a self-attention mechanism, with the resulting weights normalized by a softmax function. A BiLSTM is employed to compress the temporal representation of different features, leveraging its bidirectional architecture to capture contextual information from both directions of the sequence simultaneously. The fusion model is trained using the backpropagation algorithm, optimizing parameters and mitigating overfitting through a cross-entropy loss function combined with an L2 regularization term. Finally, the resulting feature vector is fed into a sigmoid function to output the final dropout prediction. | M12: Deep learning | N12: The proposed model was benchmarked against baseline models, specifically Support Vector Machine (SVM), standalone LSTM, standalone BiLSTM, and CNN-BiLSTM (without the self-attention mechanism). Performance was evaluated using Area Under the Receiver Operating Characteristic curve (AUROC), Area Under the Precision-Recall Curve (AUPRC), Accuracy, and F1-score. | O12: Table 3: The proposed fusion model outperformed all evaluated baseline models across all metrics, achieving an AUROC of 0,871, an AUPRC of 0,873, an accuracy of 0,868, and an F1-score of 0,864. | P12: The authors acknowledge the limitations of the proposed model, noting that a subset of students in the dataset exhibited short learning periods, thereby generating sparse behavioral data. Consequently, the extracted feature representations for these behavioral patterns may be insufficient, potentially compromising the overall performance of the fusion model. To address this issue, future work will involve conducting further experiments leveraging richer behavioral datasets to enhance the effectiveness of the fusion model. | Q12: Class imbalance | R12: The authors did not address ethical or privacy implications, nor did they mention the requirement of informed consent from the students included in the dataset.
A13: Students’ engagement prediction in online learning context via face emotion and data features with improved LinkNet and Bi-LSTM architecture | B13: 10.1007/s12652-025-04997-x | C13: Maddu, Rama Bhadra Rao and Murugappan, S. | D13: August 4, 2025 | E13: Scopus, Journal of Ambient Intelligence and Humanized Computing, Springer Nature | F13: India | G13: Classifying student engagement through the facial expression image processing presents technical challenges regarding both hardware and accuracy. To address this issue, the study proposes a new hybrid approach: ImLN-Bi-LSTM. This model captures subtle patterns in facial expression images along with students' behavioral information. While the Bi-LSTM network captures patterns in long-term temporal data, LinkNet enhances performance by effectively capturing spatial and spectral information. | H13: The study utilizes the CK+ dataset, containing 981 facial expression images, and the OULAD dataset, which includes academic performance data. These datasets are combined for a multimodal analysis aimed at capturing student engagement. A Gaussian filter is applied to enhance image quality, while Min-Max normalization is used for the performance data (Sections 3.1.1 and 3.1.2). Independent features, I-SLBT and LGXP (Sections 3.2.1.1 and 3.2.1.2), are extracted from the facial expression images. Statistical metrics—specifically the mean, median, and standard deviation—are derived from the performance variables (Section 3.2.2.1). Finally, I-EF Entropy is proposed to more easily capture engagement relationships within the data (Section 3.2.2.2). | I13: Online | J13: The CK+ dataset originally consisted of seven emotions: anger, contempt, disgust, fear, joy, sadness, and surprise. However, anger, disgust, and contempt were excluded due to their rare occurrence. The OULAD dataset features seven courses (modules) taught across two semesters per year and captures student activities on the platform, such as reading course materials, participating in discussion forums, submitting assignments, and checking grades. It also includes demographic variables such as location, age group, education level, gender, and any reported disabilities. Students are categorized using four final outcome labels: distinction, withdrawn, fail, and pass. | K13: Academic records, Demographic data, Multi-modal data | L13: The proposed hybrid classification model, based on LinkNet (with an enhanced loss function) and Bi-LSTM, captures intrinsic details within the datasets. Bi-LSTM is utilized to extract patterns from performance data, while LinkNet extracts facial expressions from images. The objective of the model is to classify students into four engagement classes: (Distinction, Happy), (Withdrawn, Sad), (Fail, Fear), and (Pass, Surprise). | M13: Deep learning | N13: The authors evaluated several performance metrics for the proposed model, highlighting accuracy, preprocessing time, and spatial complexity. | O13: The proposed model achieved a higher accuracy than all evaluated baseline models (0,952), as well as the best preprocessing time (55,21 s) and spatial complexity (0,09 KB). | P13: The authors report that the lack of a comprehensive investigation into data privacy—specifically regarding the long-term preservation of facial data—introduces risks of data breaches and limits generalizability across diverse student populations, representing major limitations of the proposed study. | Q13: Privacy concerns | R13: See "Reported Barriers". Although the authors recognize the need to investigate data privacy issues, they did not do so.
A14: One Aggregated Approach in Multidisciplinary Based Modeling to Predict Further Students’ Education | B14: 10.3390/math10142381 | C14: Delović, Milan Ran and Aleksić, Aleksandar and Radovanović, Radovan and Stojanović, Vladica and Čabarkapa, Milan and Delović, Dragan Ran | D14: July 6, 2022 | E14: Scopus, Mathematics, MDPI | F14: Serbia | G14: This study employed an aggregated framework combining traditional regression analysis with the Analytic Hierarchy Process (AHP). Additionally, ReliefF—a modern machine learning feature selection and ranking algorithm—was applied. Finally, a J48 decision tree classifier was used for aggregation. Ultimately, these models were implemented to predict students' future academic specialization choices based on their first-year academic performance. | H14: The proposed model was applied to a sample of 290 graduates from the Academy of Criminalistic and Police Studies, spanning the period 2006–2016. Specifically, this included 83 students from the Security Department (SD), 114 from the Criminology Department (CD), and 93 from the Police Department (PD). | I14: In-person | J14: The monitored features consisted of the students' grades in 10 common first-year undergraduate courses (modules S1–S10). | K14: Academic records | L14: Linear Regression: A traditional statistical method used to estimate the influence of course grades (independent variables) on department choice (dependent variable); Analytic Hierarchy Process (AHP): A mathematical multi-criteria decision-making method employed to determine the subjective importance of attributes (criteria); ReliefF Algorithm: A machine learning technique used for feature ranking by evaluating the relevance of each course based on the distance to nearest neighbors of different classes; and J48 Decision Tree Classifier: Based on the C4.5 algorithm, this was applied to perform the actual classification and validate prediction accuracy using the selected feature sets. | M14: Machine learning | N14: Performance metrics were derived from the confusion matrices of the evaluated models, specifically accuracy, precision, recall, F1-measure, and AUC-ROC. | O14: The aggregation model was compared to the baseline ReliefF + J48 model, with the baseline achieving superior results: 88,3% accuracy, 87,8% recall, 88,0% F1-score, and 85,3% AUC using 3 features. Conversely, the proposed model yielded 87,6% accuracy, 87,8% recall, 87,0% F1-score, and 79,4% AUC. However, despite the baseline's higher performance, the authors consider the proposed aggregated model promising as a cross-verification system. That is, it sacrifices a small margin of overall accuracy in exchange for multidisciplinary confidence that the selected variables are indeed the correct predictors of student behavior. | P14: The authors explicitly state that the proposed model exhibits no significant limitations. | R14: The authors do not discuss ethical or data privacy issues in detail, nor do they address informed consent or anonymization procedures for the monitored students.
A15: Predicting and Understanding Student Learning Performance Using Multi-Source Sparse Attention Convolutional Neural Networks | B15: 10.1109/TBDATA.2021.3125204 | C15: Zhang, Yupei and An, Rui and Liu, Shuhui and Cui, Jiaqi and Shang, Xuequn | D15: November 4, 2021 | E15: Scopus, IEEE Transactions on Big Data, IEEE | F15: China | G15: This study aims to predict and analyze student academic performance through the proposed MsaCNN model, framing grade prediction as a general pattern recognition problem that integrates students' knowledge development with structured course characteristics. | H15: The dataset comprises records from 5.021 students across three major programs at Northwestern Polytechnical University in Xi’an: 1.463 in Computer Science and Technology (CST), 1.621 in Software Engineering (SE), and 1.937 in Electronic Information Engineering (EIE). | I15: In-person | J15: The system leverages student demographic features (such as nationality and academic standing), historical grade records (hierarchically organized by term and category), academic logs, and course attributes (including credits, term, and instructor age). | K15: Academic records, Demographic data | L15: The primary proposed model is the Multi-source Sparse Attention Convolutional Neural Network (MsaCNN), which is benchmarked against baseline methods including Logistic Regression, SVM, KNN, Decision Trees, Random Forest, and Multi-layer Perceptrons. | M15: Deep learning | N15: Model performance was evaluated using Accuracy (ACC), weighted F1-score, and the Area Under the ROC Curve (AUC), alongside statistical significance tests such as the paired t-test and DeLong's test. | O15: The MsaCNN model consistently outperformed all baseline methods across all datasets, achieving, for instance, improvements of up to 11% in both F1-score and accuracy over Random Forest on the CST dataset. Beyond prediction, the model enabled the construction of course association maps, unveiling dependency and prerequisite relationships among core computer science courses. | P15: Reported limitations include the need to investigate potential biases across demographic attributes beyond gender, as well as the model's current inability to incorporate pre-existing, real-world prerequisite structures. | Q15: Model generalization | R15: Although the study addresses the normalization and processing of real-world university data, it lacks explicit details regarding informed student consent or compliance with specific data protection regulations, such as the GDPR.
A16: Early warning and recommendation system for undergraduate students at higher education institutions based on machine learning methods | B16: 10.7717/peerj-cs.3792 | C16: Taqatqeh, Sameh and Agoyi, Mary | D16: May 8, 2026 | E16: Scopus, PeerJ Computer Science, PeerJ | F16: Cyprus | G16: A comparative analysis of 15 machine learning classifiers; SHAP-based explainability for model transparency; a recommendation module for identifying root causes (e.g., course mismatch). | H16: Sample Size: 2.120 student-semester records (in-person environment); Class Distribution: 401 "warning" instances vs. 1.719 "good standing" instances. | I16: Hybrid | J16: The model analyzed exactly 12 features: college name, program name, high school average, school section, semester, year, GPA (per semester), SCGPA (program cumulative), CGPA (overall cumulative), passed hours, program hours, and student status. | K16: Academic records | L16: Traditional: Naïve Bayes (NB), K-Nearest Neighbors (KNN), Logistic Regression (LR), Decision Trees (DT), Support Vector Machines (SVM). Ensemble: Random Forest (RF), XGBoost, LightGBM, CatBoost, AdaBoost. Hybrid/Advanced: Stacking Ensemble, Voting Classifier, Bagging + Feature Selection, Boosting + GridSearch, Rule-Based + ML Classifier. Experimental Framework: A "Temporal Prediction" setup where features from Semester "n" are used to predict the student's status at the start of Semester "n+1". | M16: Ensemble learning | N16: Accuracy, Recall, AUC, F1-Score, and Precision. | O16: Feature selection (Experiment 2) improved accuracy across models by 0,5% to 1,5% compared to using all features (Experiment 1). Top Performer: The Boosting + GridSearch model (Ensemble Learning) achieved the highest validated metrics: Accuracy 89,7%, Recall 0,92, AUC 0,92, F1-score 0,90, and Precision 0,88. SHAP analysis identified the top three predictors as GPA, Passed hours, and CGPA. The researchers noted a "complementary character" in their feature selection; while correlation-based methods highlighted linear associations, ranking-based methods (Information Gain, Relief) captured non-linear interaction effects, such as the impact of "Program hours" and "School section." | P16: Predictions are static (end-of-semester data only) and restricted by the lack of psychological or real-time behavioral markers (e.g., student motivation). | Q16: Data availability, Privacy concerns | R16: The research leverages "Explainable AI" as a primary ethical framework to ensure stakeholder trust, though it identifies a deficit in the discussion of formal data privacy regulations like GDPR.
A17: Predicting Student Dropout Through Text and Media Content Analysis of VKontakte Profiles | B17: 10.1109/ACCESS.2025.3550817 | C17: Gorshkov, Sergei S. and Ignatov, Dmitry I. and Chernysheva, Anastasia Yu | D17: March 21, 2025 | E17: Scopus, IEEE Access, IEEE | F17: Russia | G17: This study aims to identify social media analytics techniques for characterizing students, develop a comprehensive digital profile that accounts for temporal patterns in shared content, and build an accurate, interpretable model for predicting academic dropout risk. | H17: The total sample consisted of 3.454 students across 22 faculties at Tomsk State University. | I17: In-person | J17: The system monitors students' digital footprints on the VKontakte social network, extracting counts of photos, videos, and posts, along with distributions across 50 scene types, 35 visual contexts, 23 textual topics, 9 emotional states, 20 music genres, and institutional (faculty) affiliations. | K17: Multi-modal data | L17: Binary classification algorithms based on decision trees were applied, specifically Random Forest and gradient boosting models such as CatBoost and LightGBM, integrated with the proposed Weighted Neighborhood Feature Aggregation (WNFA) method to incorporate friendship graph data. | M17: Ensemble learning | N17: To validate model performance in the presence of class imbalance, ROC-AUC (Area Under the ROC Curve) and Balanced Accuracy metrics were used. | O17: The CatBoost model achieved the highest performance when integrating recent and historical content with friend graph data (WNFA), reaching a ROC-AUC of 0,802 and a Balanced Accuracy of 0,749. Feature importance analysis revealed that academic engagement and family photos mitigate dropout risk, whereas entertainment and humor content elevate it. | P17: The main limitations include the exclusive reliance on the VK social network, data noise caused by outdated profiles, the restriction to public information that may be limited by privacy settings, and generalizability bias due to focusing on a single Russian institution. | Q17: Data availability, Model generalization | R17: The project ensured GDPR compliance and obtained approval from the Ethics Committee of the TSU Faculty of Psychology, ensuring participants' informed consent, data anonymization, and transparency in algorithm usage to prevent discrimination.
A18: Application of GA-BP Neural Network in Online Education Quality Evaluation in Colleges and Universities | B18: 10.1155/2022/7846247 | C18: Sun, Guodong | D18: May 20, 2022 | E18: Scopus, Mobile Information Systems, Hindawi | F18: China | G18: This work proposes and implements an academic performance prediction algorithm based on a hybrid neural network architecture termed DTGA-BP. The practical objective is to predict students' future grades using their current and past performance while providing feedback on online class quality to instructors. This approach enables a better understanding of students' knowledge levels and informs pedagogical strategies aimed at improving instructional efficiency. | H18: Data were collected from 99 undergraduate Communication Engineering students at a Chinese university. Following sample refinement, records for 80 students were retained. | I18: Online | J18: Final grades (0–100) were collected for the 12 courses with the highest correlation coefficients (Table 2) taken by the students. The baseline model incorporated all 12 variables, whereas the proposed model used only 6 (those with a correlation coefficient above 0,35). | K18: Academic records | L18: This study presents a novel methodological approach of high technical rigor that integrates data mining techniques to predict academic performance more efficiently—achieving comparable efficacy at a lower computational cost—than traditional methods. The approach employs Pearson correlation to reduce input data dimensionality by selecting only core courses with significant influence. The structure of the backpropagation (BP) neural network is refined using a decision tree (DT) to reduce model complexity and training time. Furthermore, a genetic algorithm (GA) is introduced to optimize the network's initial weights and thresholds. | M18: Machine learning | N18: The predictive performance of the developed model is presented in Table 3 and compared against a benchmark from the literature—specifically, a standard Backpropagation (BP) Neural Network. The evaluation metrics employed were Root Mean Square Error (RMSE) and training time (in seconds). | O18: Simulations were conducted in MATLAB R2016a. The proposed model (DTGA-BP) achieved an RMSE of 3,1, compared to 7,9 for the baseline model, demonstrating superior predictive accuracy and confirming the effectiveness of the proposed algorithm. Furthermore, the training time was reduced from 0,2388 s (BP) to 0,1469 s (DTGA-BP), as shown in Table 1. | P18: No limitations were reported, although the sample size may be considered small. | R18: Ethical considerations were not addressed. Although the dataset may have been provided by Shijiazhuang University of Applied Technology, no procedures regarding informed consent or student data protection were reported.
A19: Research on data modeling and strategy optimization algorithm of teacher guidance behavior for precision teaching | B19: 10.1117/12.3082462 | C19: Dandan, Zhang and Hongtao, Cui | D19: August 28, 2025 | E19: Scopus, International Conference on Algorithms, Image Processing, and Deep Learning (AIPDL 2025), SPIE | F19: China | G19: Pedagogical actions grounded in educational data processing can benefit from more targeted and precise corrective interventions, accelerating response times and improving overall teaching quality. In this context, this study proposes a dynamic feature extraction method based on a multimodal spatial-temporal graph neural network (MST-GNN), as well as a dual-layer reinforcement learning optimization algorithm (DRL-Tutor). | H19: Data were collected in a smart classroom environment equipped with six 1080p cameras for panoramic and facial expression monitoring, eight microphone arrays for audio signal recording, and a smart blackboard with automated handwritten content capture. The sample comprised records from two mathematics classes totaling 240 students and 8 teachers each. The system processed 10.000 five-minute video clips. The experimental group adopted the interventions suggested by the DRL-Tutor algorithm, whereas Control Group A followed an experience-based teaching strategy (without technological assistance), and Control Group B utilized a fixed rule-based script regardless of student reactions or lesson pacing. | I19: In-person | J19: The MST-GNN framework builds a graph structure incorporating spatial and temporal features by integrating classroom environment data (Figure 1). This encompasses spatial information (teacher positioning, student seating arrangements, and teaching resource distribution), temporal information (questions, explanations, group activities, and feedback), and multimodal information—including audio (pitch, speech rate, and vocabulary), visual cues (gestures and facial expressions), and text (blackboard content semantics and instructional materials). | K19: Academic records, Multi-modal data | L19: The proposed model relies on multimodal and temporal feature extraction via a multimodal spatial-temporal graph neural network (MST-GNN), overcoming the constraints of traditional static encoding and enabling behavioral analysis to evolve over time. Subsequently, the extracted data are processed by a dual-layer deep reinforcement learning optimization algorithm (DRL-Tutor). This algorithm combines the exploitation of prior knowledge (historical teaching data) with real-time feedback fine-tuning (such as student attention and reactions), preventing the system from needing to learn from scratch for each new cohort or classroom scenario. | M19: Reinforcement learning | N19: The evaluation period lasted 8 weeks, with performance outcomes compared between the experimental group and the control groups. The analysis evaluated knowledge retention rates, student participation rates, cognitive deviation correction speed, and cognitive level scores. The developed predictive model was assessed for accuracy, processing latency, and feature space metrics—specifically minimum inter-class distance and average inter-class similarity. | O19: Table 2: Minimum inter-class distance and average inter-class similarity were higher for the MST-GNN model across all three analyzed behavioral categories. Figure 3: The DRL-Tutor model achieved superior accuracy compared to the traditional static model (92,1% vs. 68,3%). Table 3: Knowledge retention was significantly higher in the experimental group than in the control groups (83,2% vs. 71,5% and 68,9%), as were student engagement rates (88,7% vs. 76,2% and 73,4%) and the time required to identify and correct conceptual errors (3,2 min vs. 8,7 min and 9,1 min). Figure 4: Cognitive level gain was markedly higher in the experimental group, showing an 18,5-point advantage after 6 weeks. Figure 5: Finally, the proposed edge-based model demonstrated a substantial reduction in processing latency (112 ms for 20 concurrent requests) compared to the traditional cloud-based model (298 ms for 20 concurrent requests). | P19: The authors did not address any study limitations. For instance, the deployment of the NVIDIA Jetson AGX edge module poses a challenge to adapting the developed system to other institutions due to the high monetary cost of the device. | R19: The authors did not discuss any ethical implications of the study, despite camera monitoring in the smart classroom raising concerns regarding data protection and privacy. For the experiment, the authors made no mention of anonymization protocols or informed consent forms for the 480 students and 16 teachers involved.
A20: Few Adjustable Parameters Prediction Model Based on Lightweight Prefix-Tuning: Learning Session Dropout Prediction Model Based on Parameter-Efficient Prefix-Tuning | B20: 10.3390/app142310772 | C20: Lu, Yuantong and Wang, Zhanquan | D20: November 21, 2024 | E20: Scopus, Applied Sciences, MDPI | F20: China | G20: The main objective of this study is to propose FAP-Prefix, a solution for Learning Session Dropout Prediction (LSDP). It leverages prefix-tuning to maintain high accuracy even under data-scarce conditions, effectively overcoming the limitations of conventional fine-tuning. | H20: The total study sample comprises data from 462.395 users across the three datasets: 297.915 students from EdNet-KT4, 112.448 from XuetangX, and 52.032 users from Orthografietrainer. | I20: Online | J20: The monitored variables focus on sequential behavior, including action types (e.g., play, pause, quit), timestamps, dwell time (cursor time), platform used (mobile or web), item identifiers, problem response correctness, and session IDs. | K20: VLE activity log | L20: This study applies the proposed FAP-Prefix model (built upon variants of BERT, ALBERT, and UniLM) and evaluates it against several baseline models, including LSTM, GRU, SVR, M3PP, DAS, and MLP. | M20: Deep learning | N20: To evaluate model performance, three primary metrics were used: Area Under the ROC Curve (AUC), Accuracy (ACC), and F1 Score. | O20: The FAP-Prefix model (ALBERT variant) outperformed state-of-the-art baselines across all scenarios, achieving AUC scores of 0,9012 on EdNet-KT4, 0,8239 on XuetangX, and 0,9193 on Orthografietrainer. Furthermore, the model proved to be significantly more parameter-efficient, drastically reducing the number of trainable parameters compared to full fine-tuning. | P20: The authors identify two key limitations: first, the exclusion of static features (such as user demographics and course metadata), which may hinder profile differentiation; second, that excessively long prefix lengths can introduce noise and degrade model attention. | Q20: Privacy concerns | R20: Regarding ethical considerations, the study states that Institutional Review Board (IRB) approval and informed consent statements are "Not applicable"; however, it notes that the data are available from the authors upon reasonable request for research purposes.
A21: Achieving optimal trade-off for student dropout prediction with multi-objective reinforcement learning | B21: 10.7717/peerj-cs.2034 | C21: Pan, Feng and Zhang, Hanfei and Li, Xuebao and Zhang, Moyu and Ji, Yang | D21: April 30, 2024 | E21: Scopus, PeerJ Computer Science, PeerJ | F21: China | G21: A novel approach based on Multi-Objective Reinforcement Learning (MORL) to achieve an optimal trade-off between the earliness and accuracy of dropout prediction by modeling the problem as a Multi-Objective Markov Decision Process (MOMDP). The framework employs a vectorized reward function alongside Multi-Objective Double Deep Q-Network (MODDQN) Envelope Q-Learning to overcome the information loss typical of scalarized functions. A key advantage of this model is its ability to handle non-convex solution sets—a persistent challenge in traditional multi-objective optimization that hinders search space navigation and global optima identification. Ultimately, this work aims to discover Pareto-optimal strategies that enable dynamic system adaptation according to varying user preferences between accuracy and earliness, validated on large-scale MOOC datasets. | H21: The datasets were obtained from XuetangX (https://www.xuetangx.com/), China's largest Massive Open Online Course (MOOC) platform. The first dataset, KDDCup 2015, comprises 39 courses and 72.395 students. It spans a 30-day observation window and includes seven distinct student learning activity types, which are utilized as predictive features. The KDDCup 2015 dataset serves as a benchmark to compare the proposed method against existing techniques. The second dataset (XuetangX)—originally containing 246 courses, 202.000 students, and 22 event types—was filtered to retain courses with fewer than 350 student trajectories, resulting in a final subset of 19 courses and 23.839 students. This refined dataset was used to evaluate the robustness and generalizability of the developed model. Both datasets were split into 70% for training, 10% for validation, and 20% for testing. | I21: Online | J21: Although the specific variable names composing each dataset are not explicitly detailed in the paper, the KDDCup 2015 dataset features seven unique types of student learning activities, whereas the XuetangX dataset incorporates 22 learning event types. Nonetheless, the complete source code for this project is publicly available on GitHub at: https://github.com/leondepf/MORL-MOOC/tree/master. | K21: VLE activity log | L21: The paper proposes a novel model by reformulating the dropout prediction problem as a Multi-Objective Markov Decision Process (MOMDP), allowing conflicting objectives—accuracy and earliness—to be addressed simultaneously and holistically. Practical implementation is achieved via the MODDQN algorithm. Unlike prior models, this work introduces a vectorized reward function that preserves the individual contributions of each objective, thereby avoiding the information loss associated with dimensionality reduction (scalarization). The model employs Envelope Q-Learning for policy updates, enabling a single unified network to learn a policy that covers the entire spectrum of user preferences (i.e., different trade-off weights between accuracy and earliness) without requiring retraining. Ultimately, the model aims to identify a Pareto-optimal frontier, empowering educational administrators to dynamically select the most suitable balance for their specific context. | M21: Reinforcement learning | N21: Average Accuracy (Avg. Acc.), Average Proportion Used (APU), Average Harmonic Mean (Avg. HM). | O21: KDDCup 2015: Avg. Acc.: 0,7945; APU: 8,717%; Avg. HM: 0,8496. XuetangX: Avg. Acc.: 0,7770; APU: 4,283%; Avg. HM: 0,8577. The proposed MORL model was evaluated against established baselines (LSTM-Fix, NonMyopic, ECTS, DDQN+PER, and EARLIEST), with comparative results detailed in Figures 5 and 6, as well as Table 1. MORL achieved performance comparable or superior to the baseline models. Crucially, it attained the highest Average Harmonic Mean (Avg. HM) across both datasets, confirming its superior efficacy in balancing the two competing objectives. Furthermore, the MORL agent demonstrated strong robustness by dynamically adapting to any user preference ratio without requiring retraining. Additionally, the proposed model achieved accuracy levels comparable to top-performing baselines while consuming a minimal amount of sequence data (APU 4–8%), indicating an exceptionally early prediction capability—an advantage enabled by the use of vectorized rewards. | P21: A key limitation highlighted by the authors is that the model relies on static objective weights throughout the training phase. Future research could explore dynamic weighting schemes that evolve over time. Furthermore, the current system operates with a single agent, restricting it to a preference-based single-policy framework. A natural evolution would be transitioning toward a Multi-Objective Multi-Agent Reinforcement Learning (MOMARL) paradigm, enabling more cooperative and complex solution spaces. Finally, there is a need to explore hyperparameter optimization within a hierarchical reinforcement learning framework, where an auxiliary agent could sequentially select optimal parameters for the system. | R21: Both datasets utilized were thoroughly anonymized to ensure compliance with ethical guidelines and privacy regulations.
A22: Automated Student Engagement Detection Using Hybrid Deep Learning and Machine Learning Techniques | B22: 10.1109/FIE63693.2025.11328252 | C22: Abdelhamid, Sherif E. and Aly, Mona | D22: Date of Conference: 02-05 November 2025; Date Added to IEEE Xplore: 13 January 2026 | E22: Scopus, 2025 IEEE Frontiers in Education Conference (FIE), IEEE | F22: United States | G22: This study makes two complementary contributions: first, a systematic literature review to identify the state of the art in applying Artificial Intelligence to classify student engagement from images (RQ1); second, an empirical evaluation of two distinct approaches: training Deep Learning models for direct engagement classification (RQ2), and using Deep Learning for feature extraction followed by Machine Learning for classification (RQ3). These findings culminated in the development of EduWatch, a web-based tool that integrates the trained models to enable real-time detection and analysis of student engagement. | H22: The dataset was constructed and evaluated to capture varying levels of student engagement across both face-to-face and virtual learning environments. | I22: Hybrid | J22: Features were extracted from images of students in both physical and online classrooms using Deep Learning models, representing observable physical behaviors. | K22: Multi-modal data | L22: The study evaluates the performance of three standalone Deep Learning models: MobileNet, VGG16, and ResNet50. Subsequently, it analyzes a hybrid approach that uses these Deep Learning models for feature extraction, followed by classification using Machine Learning algorithms—specifically Logistic Regression, Random Forest, and KNN—as well as an ensemble model combining them via soft voting. | M22: Machine learning | N22: Accuracy, Precision, Recall, and F1 Score. | O22: The performance metric values are presented in Figures 6, 7, and 8. In the first experiment, VGG16 achieved the highest performance among the standalone Deep Learning models, with an accuracy of 93,33% and an F1 score of 93,75%. In the second experiment, Logistic Regression obtained the best performance, reaching 95,99% accuracy and a 96,01% F1 score. These results confirm that the second approach—combining Deep Learning for feature extraction with Machine Learning for classification—achieved the overall best performance. | P22: In the future work section, the authors implicitly acknowledge the limitation of relying solely on static images by expressing their intention to incorporate additional modalities, such as video sequences, voice input, and facial emotion analysis. | Q22: Data availability | R22: Although the authors present a custom dataset and a real-time individual monitoring tool (EduWatch), the study suffers from a critical gap in ethical integrity, as it fails to report consent protocols, compliance with data protection regulations (such as LGPD/GDPR), or measures to mitigate the privacy risks inherent to automated student surveillance.
A23: Psychometric Validation of an AI-Based Evaluation System for Identifying Discrepancies in Learning Processes | B23: 10.47738/jads.v7i2.1168 | C23: Suyasa, P. Wayan Arta and Pujawan, I. Gusti Ngurah and Divayana, Dewa Gede Hendra and Budhyani, I. Dewa Ayu Made and Sugiarta, I. Made and Candiasa, I. Made | D23: April 18, 2026 | E23: Scopus, Journal of Applied Sciences (JADS), Bright | F23: Indonesia | G23: The primary contribution of this study is the integration of the Provus Discrepancy Model with a forward-chaining AI inference engine, marking a global first in educational evaluation technology. This hybrid model achieved a 73% reduction in evaluation costs and a 67% reduction in analysis time compared to traditional manual methodologies. This finding is impactful because it demonstrates that AI can perform complex, theory-driven root-cause analysis, effectively moving evaluation from a retrospective administrative burden to a proactive diagnostic tool. | H23: The validation protocol utilized a dual-track approach involving two distinct participant groups: a panel of eight instructional evaluation experts and a field-test cohort of 400 undergraduate students (in-person environment). Critically, the student sample was split into 200 for pilot testing and 200 for confirmatory analysis to ensure statistical validity. This split-sample methodology provides the high level of statistical power necessary to confirm the system's psychometric properties and diagnostic accuracy across diverse university settings. | I23: In-person | J23: The system monitors student data across the four hierarchical stages of the Provus model: Design, Installation, Process, and Product. Crucially, the system also tracks fairness attributes through Differential Item Functioning (DIF) testing, which confirmed no demographic bias. The inclusion of these fairness attributes is the critical factor for wider academic implementation, as it addresses the ethical requirement of algorithmic non-discrimination and ensures that the AI’s "judgment" is equitable across all student demographics. | K23: Academic records, Demographic data | L23: The system utilizes a Rule-Based Expert System powered by a forward-chaining inference engine using "if-then" logic. This specific AI mechanic is vital for auditability; unlike "black box" neural networks, the forward-chaining approach allows auditors to trace every step of the AI's reasoning from observed classroom data to the final discrepancy flag. This transparency ensures that institutions can explain and justify the "decisions" made by the AI, which is a requirement for high-stakes educational diagnostics. | M23: Machine learning | N23: Model performance was evaluated through classification metrics including diagnostic accuracy (92,4%), F1-score (89,9%), and a Kappa agreement of 0,86, alongside psychometric fit indices (CFI = 0,94; RMSEA = 0,054). The high Kappa agreement is particularly significant as it validates that the AI's reasoning matches "expert-level" human diagnostics. This dual-layer validation ensures the system is not only computationally efficient but also theoretically aligned with the principles of educational measurement. | O23: The AI identified 45 unique discrepancy patterns, outperforming manual evaluation methods by a margin of 47,4 percentage points in accuracy. The "So What?" of this data point is profound: it represents the elimination of human subjectivity in educational diagnostics. By detecting subtle, non-linear interactions between the Design and Process stages that human evaluators often overlook, the system provides a level of diagnostic precision previously unattainable through manual monitoring. | P23: The authors documented significant barriers to sustainability, primarily the current absence of training modules and video tutorials for academic staff. This identifies a "human-in-the-loop" bottleneck where the system's diagnostic output may be underutilized if lecturers lack the training to translate AI flags into pedagogical interventions. Documenting these barriers provides a clear roadmap for the next phase of institutional implementation, focusing on the human-centered elements of AI adoption. | R23: The study demonstrated rigorous adherence to the 1964 Helsinki Declaration, including anonymization protocols and the acquisition of written consent from all experts and students. The research was formally approved by the institutional IRB at Universitas Pendidikan Ganesha, and all data were stored on restricted-access secure servers. This commitment to ethical rigor ensures that the system’s implementation is compatible with international standards for student privacy and institutional accountability.
A24: Investigating the Importance of Demographic Features for EDM-Predictions | B24: 10.5281/zenodo.8115647 | C24: Cohausz, Lea and Tschalzev, Andrej and Bartelt, Christian and Stuckenschmidt, Heiner | D24: July 5, 2023 | E24: Scopus, 16th International Conference on Educational Data Mining, International Educational Data Mining Society | F24: Germany | G24: This study analyzes the impact of including demographic data in training academic success prediction models, testing the hypothesis that study-related variables (such as grades and attendance) act as mediating factors. That is, if demographic background influences performance, this effect is already captured in historical performance metrics. Consequently, incorporating demographic attributes is redundant for model accuracy and technically problematic: it risks overfitting on underrepresented groups and propagating historical dataset inequalities—such as instructors' conscious or unconscious biases toward specific genders or ethnicities—thereby perpetuating unfair predictions. The findings demonstrate that although models utilize these sensitive attributes when available, doing so does not improve performance, supporting the recommendation to exclude them to protect student privacy and promote algorithmic fairness. | H24: The experiment used four public datasets: two from online learning systems and two from in-person education. Specifically, "Engineering" represents in-person higher education, "PortSecStud" covers in-person secondary education, "xAPI-Edu" pertains to general online learning, and "OULAD" addresses online higher education. As shown in Table 1, the sample sizes for these datasets were 12.411, 1.044, 480, and 22.437, respectively. Additionally, variable types (e.g., demographic data, performance records) vary across datasets (Table 2). | I24: Hybrid | J24: The variables for each dataset are detailed in Table 2 and include academic performance records, demographic data, and engagement activities, as well as categorical (discrete) attributes and other domain-specific variables. Categorical values were converted into numerical representations using One-Hot Encoding (OHE). For high-cardinality features, Ordinal Encoding, Target Encoding, CatBoost Encoder, and 5-fold cross-validated Generalized Linear Mixed Model (5CV-GLMM) encoding were applied. Continuous variables were standardized to zero mean and unit variance, and missing values were addressed by listwise deletion where necessary. | K24: Academic records, Demographic data | L24: The experiments evaluated Generalized Linear Models (GLMs) and XGBoost (a non-linear method based on Ensemble Learning, which delivered the best performance), trained on datasets comprising only demographic variables, only performance records, or both, alongside comparison with baseline models (Table 4). Lasso regression was applied for regularization and overfitting prevention in the regression models, while Logistic Regression with L2 penalty was implemented for classification tasks. Both model families underwent hyperparameter optimization (HPO) via the hyperopt library using Bayesian optimization. | M24: Ensemble learning | N24: Model performance was evaluated using Root Mean Squared Error (RMSE) for regression tasks and F1-score for classification tasks. To assess the importance of each feature in the predictions, the author's analyzed the learned coefficients of the linear models and the feature importance metrics for XGBoost, following the methodology described in Section 5.6. | O24: RQ6: The lack of statistical significance in comparing categorical variable encoding techniques indicates that this preprocessing step does not meaningfully impact predictive performance. RQ5: Although linear models are sufficient in many contexts, non-linear methods achieve superior performance on larger and more complex datasets. RQ2: When learning-related information is available, demographic data becomes unnecessary. RQ4: Consequently, including demographic data yields models that leverage demographic features despite their lack of necessity. RQ1: In the absence of learning-related information, demographic data can account for variance in academic success. RQ3: Authors thus conclude that models predicting student success should rely solely on study-related features rather than demographic characteristics. | P24: The authors highlighted concerns regarding the difficulty of anonymizing demographic data, which are considered sensitive attributes that could potentially be used to re-identify students. To share data securely, pseudonymization techniques such as k-anonymity must be employed; however, the authors describe achieving such privacy standards as "extremely difficult" and note that they may degrade data utility due to required aggregation (binning). Furthermore, demographic attributes are typically categorical and often exhibit high cardinality (numerous unique values), rendering the feature engineering process non-trivial. Standard correlation-based feature selection techniques tend to improperly select demographic variables because they correlate with academic outcomes. Finally, the authors suggest evaluating additional datasets as a direction for future work. | R24: The core research question of this study addresses the inherent ethical concerns of using demographic data to train academic success prediction models. Incorporating such sensitive attributes risks propagating historical dataset inequalities—such as instructors' conscious or unconscious biases regarding gender or ethnicity—thereby perpetuating unfair predictions. Furthermore, it can lead to overfitting on underrepresented groups: for instance, if a dataset includes only one Hispanic student who has two children and low academic achievement, the model might incorrectly infer that this demographic profile universally predicts poor performance.
A25: Cognitive Web Service-Based Learning Analytics in Education Systems Using Big Data Analytics | B25: 10.4018/IJeC.316658 | C25: Bin, Li | D25: 2023 | E25: Scopus, International Journal of e-Collaboration, IGI Global Scientific Publishing | F25: China | G25: The objective of this study is to propose the Educational Clustering Big Data Mining System (ECBDMS), integrating it with Cognitive Web Services for Learning Analytics (CWS-LA) to perform secure data categorization, facilitate decision-making, and predict students' academic performance and qualities in digital educational systems. | H25: The validation of the proposed system was conducted through a computational simulation using a dataset containing records of 395 students. | I25: Online | J25: The system analyzes 33 different attributes, including variables captured during digital sessions such as average active hours, average idle time, keystroke counts, and total entries related to students' academic activities. | K25: VLE activity log | L25: The study uses a Characterization Prediction Algorithm, integrating various data mining and machine learning techniques—such as K-means clustering, Random Forest Regression, K-Nearest Neighbors (KNN), and Decision Trees—all operating in conjunction with cognitive web services. | M25: Ensemble learning | N25: The effectiveness of the proposed system was evaluated through the clustering error rate, performance gain, prediction ratio, learning percentage, and prediction accuracy, as well as the use of Mean Absolute Deviation (MAD) to assess forecast precision. | O25: The ECBDMS model outperformed other methods, achieving a prediction accuracy of 97,1%, a performance gain of 92,8%, a prediction ratio of 88,6%, and a learning percentage of 94%, with a clustering error rate of just 2,3%. | P25: The authors identify key challenges in processing large data volumes from heterogeneous sources and mitigating security vulnerabilities in digital databases prone to attacks, suggesting that enhanced data protection measures are needed for future work. | Q25: Privacy concerns | R25: The article highlights that the cognitive services used do not retain data post-processing, thereby facilitating compliance with privacy laws. However, it acknowledges that institutionally stored student digital records remain a ongoing concern regarding information security.
A26: An approach to dealing with incremental concept drift in personalized learning systems | B26: 10.1109/CogMI56440.2022.00029 | C26: Allogmany, Bander and Josyula, Darsana | D26: Date of Conference: 14-17 December 2022; Date Added to IEEE Xplore: 13 March 2023 | E26: Scopus, 2022 IEEE 4th International Conference on Cognitive Machine Intelligence (CogMI), IEEE | F26: United States | G26: The main objective of this paper is to propose and evaluate an approach capable of handling the phenomenon of concept drift, specifically incremental drift, in personalized learning systems. Concept drift is a phenomenon that occurs in non-stationary data streams, where the relationships between variables change over time. This phenomenon causes the performance of machine learning models to decrease over time, as these models lose efficiency when attempting to process data whose statistical distributions have changed. Concept drift occurs because predictive models are trained based on historical behavioral patterns. When the context changes—due to social, economic, or environmental factors, or global crises such as the COVID-19 pandemic—student behavior changes, rendering old patterns obsolete for new predictions. | H26: The Open University Learning Analytics Dataset (OULAD), which comprises records of student interactions in Virtual Learning Environments (VLEs), was used and encompasses two course types: STEM (Science, Technology, Engineering, and Mathematics) and Social Sciences. The database contains interactions from 32.593 students enrolled in 22 modules between 2013 and 2014. After preprocessing, the number of records was refined to 28.174, categorized into three main groups: success, failure, and withdrawal. | I26: Online | J26: A total of 52 features were extracted from the dataset, including demographic information (personal info, background, gender, age), virtual environment interactions (number of clicks), and module performance (total score, quiz grades, and assignments). All features are listed in Table 2. The total number of clicks attribute was used to simulate incremental concept drift, as it is a continuous value that reflects gradual changes in student behavior over time. | K26: Academic records, Demographic data, VLE activity log | L26: Initially, the authors artificially introduced concept drift into the dataset to create gradual behavioral changes. In the first methodological stage, a Long Short-Term Memory (LSTM)-based Autoencoder architecture was applied to extract sequential features and capture hidden temporal relationships, mapping the raw data into a low-dimensional latent space. After training this autoencoder to minimize reconstruction loss, its first two layers were extracted and used to generate the inputs for the second stage. This final stage consists of a Support Vector Machine (SVM) classifier—therefore, the forecasting task is performed using Machine Learning—which is trained exclusively on these compressed and refined features to predict academic performance (pass, fail, or withdraw). | M26: Machine learning | N26: Accuracy was evaluated, and the performance of the proposed model was measured based on its ability to handle different types of drifts compared to the LSTM and SVM baselines. First, all models were trained on the dataset without concept drift, and then on the dataset with concept drift. Finally, performance was measured to evaluate how the models handled the addition of concept drift. | O26: The baseline models showed a decline in accuracy after the insertion of concept drift: 74,6%–69,21% (SVM) and 72,86%–65,95% (LSTM). On the other hand, the proposed hybrid model achieved a higher post-drift accuracy: 72,56%. | P26: The only concept drift addressed in the article is incremental drift. The authors then suggest, for future research, validating the proposed model on "other types of drift". | Q26: Model generalization | R26: While the study relies on a publicly available dataset, ethical considerations and data privacy aspects were not explicitly discussed.
A27: Evaluation of Machine Learning Models to Predict Student Academic Performance Using Structured Educational Data | B27: 10.3844/jcssp.2026.1721.1742 | C27: Patel, Hardik Ishwarbhai and Patel, Dharmendra | D27: April 20, 2026 | E27: Scopus, Journal of Computer Science, Science Publications | F27: India | G27: The study introduces a dual-prediction framework capable of estimating CGPA and classifying Pass/Fail outcomes. Its primary contribution is the creation of a 20.995-record dataset that integrates academic SIS data with socio-economic indicators. Furthermore, the systematic 3-step feature selection pipeline (Filter; Random Forest; RFE) establishes a repeatable, high-integrity methodology for institutional research. | H27: The total population consisted of 20.995 records, but the experimental sample was reduced to 141 records. From an auditor's perspective, while this sample size was calculated for statistical representativeness (95% confidence, 5% margin of error), the decision to use such a small subset for "computational feasibility" in an era of high-performance computing is a methodological weakness that necessitates cautious interpretation of the results. | I27: In-person | J27: The study monitored 95 attributes, later refined to 22. These include: Academic Parameters: 10th/12th results, attendance, unit tests, and backlog history. Socio-Economic Parameters: Parental qualifications (PEI), family monthly income, and residential status. Combining internal performance with external cultural capital (PEI) creates a holistic student profile. | K27: Academic records, Demographic data | L27: The study applied: Regression: SVR, XGBoost, Linear Regression, and Gradient Boosting. Classification: Logistic Regression (Balanced) and Gaussian Naive Bayes. A technical turning point was the use of the Radial Basis Function (RBF) kernel in the SVR model. This allowed the model to map non-linear socio-economic dependencies that the Linear Regression baseline (initial R² of 0,5123) failed to capture. | M27: Machine learning | N27: Regression: R², Mean Squared Error (MSE), and Mean Absolute Error (MAE). Classification: Accuracy, Precision, Recall, and F1-score. These provide a multi-dimensional view of model strength across continuous and categorical targets. | O27: The results were exceptionally high after optimization (all Machine Learning models): SVR (Tuned): Achieved an R² of 0,9125 and a low MSE of 0,0097. Gaussian Naive Bayes: Attained 99,33% accuracy, though it exhibited the classic high-accuracy/low-recall paradox (recall of 0,5185 for the "Fail" class) due to class imbalance. Logistic Regression (Balanced): Achieved 96,34% accuracy with more equitable recall for at-risk identification. | P27: The authors noted the omission of psychological and behavioral factors (motivation, peer influence). They also acknowledged the limitation of a localized dataset and a specific algorithm set, which impacts the universality of the predictive weights. | Q27: Data availability, Model generalization | R27: The study asserts "no conflict," but lacks explicit narrative on student consent or data anonymization. This is a critical gap given the high sensitivity of attributes like "Family Monthly Income," which require stringent protection under modern data privacy standards.
A28: Quantifying the impact of student enrollment patterns on academic success using a hidden markov model | B28: 10.3390/app11146453 | C28: Boumi, Shahab and Vela, Adan Ernesto | D28: July 13, 2021 | E28: Scopus, Applied Sciences, MDPI | F28: United States | G28: The study proposes a model to classify students into three groups according to their enrollment type throughout their academic trajectory: full-time, part-time, and mixed (at times full-time, at times part-time). Subsequently, they analyze the correlation between enrollment type and the student's known academic success. Thus, the main objective is to calculate the probability of a student graduating or dropping out at different stages of their academic trajectory. Finally, the main contribution of the paper is identifying the correlation between part-time enrollment strategies and the risk of dropout and poor academic performance, evaluated for a higher education institution in the United States. | H28: Data were collected from the University of Central Florida, containing 170.000 records from 2008–2017. | I28: In-person | J28: Tables 2–5 summarize student demographic data (gender and ethnicity), semester-by-semester enrollment status (full or part-time), college affiliation, completed coursework, and reported household income. | K28: Academic records, Demographic data | L28: A Hidden Markov Model (HMM)—which is not a conventional machine learning model but rather a probabilistic and sequential statistical model—is applied to identify student enrollment strategies and characterize their respective impacts on student academic performance, as well as hypothesis tests and complementary probabilistic models, such as ANOVA, linear regression, Chi-square, Kruskal–Wallis H-test, KS2 test, and Games–Howell Multiple Comparison. | M28: Machine learning | N28: The study employs an approach to classify academic success based on correlation analysis between enrollment strategies, demographic data, and family income, with the risk of dropout and academic success. Therefore, predictive model performance metrics were not evaluated. | O28: The correlation analysis between enrollment status and average GPA indicates that full-time students achieve higher academic performance (Tables 4 and 5). Consequently, university administrators should implement strategies to support full-time enrollment, such as expanding financial aid and on-campus employment opportunities. This is particularly crucial given that lower-income students are more likely to enroll part-time (Table 3), primarily due to off-campus work commitments required to fund their education. Ultimately, the authors demonstrated that enrollment strategy correlates with the likelihood of graduation or attrition, further underscoring the need for targeted institutional intervention. | P28: Although significant, these findings are specific to a single U.S. institution and may not fully generalize to other contexts. | Q28: Model generalization | R28: The authors did not address data privacy, student informed consent regarding the datasets, or the potential ethical concerns associated with the analysis.
A29: GNN-driven modeling and prediction of multi-dimensional correlation of international medical education quality based on competence | B29: 10.1016/j.caeai.2026.100582 | C29: Yang, Ailing and Lin, Ling and Zhang, Hu and Su, Rong and Li, Yunfei | D29: April 1, 2026 | E29: Scopus, Computers and Education: Artificial Intelligence, Elsevier | F29: China | G29: This study proposes the RT-GAT model to overcome the limitations of traditional methods in international medical education assessment, which often fail to capture the multidimensional nature and temporal evolution of student competencies. | H29: The system was validated on a sample of 900 medical students across three distinct universities, representing 20 countries of origin. The paper rigorously details the data preprocessing steps—including techniques such as SMOTE for sample balancing and LOF for noise removal—and transparently discusses limitations regarding subgroup representativeness and the modeling of ethical competencies. Additionally, external validation was conducted on an independent sample of 1.000 students from ten institutions across China, the USA, India, the UK, Russia, and Nigeria. | I29: In-person | J29: Standardized theoretical exam scores, rating scales from standardized patient interviews, peer evaluation averages in group work, and demographic data—including nationality, gender, age, and enrollment history. | K29: Academic records, Demographic data | L29: It implements the Relational Temporal Graph Attention Network (RT-GAT) model, a Graph Neural Network architecture. By constructing a heterogeneous graph that integrates dimensions of knowledge, clinical practice, communication, and teamwork, the system employs relationship-sensitive attention mechanisms—such as guidance, collaboration, and feedback—grounded in educational psychology. The innovative architecture combines sine-cosine positional encoding with Bi-LSTM networks to dynamically track student progress across five educational stages, enabling a structural representation that achieved a cosine similarity of 0,91 in competency correlation modeling. | M29: Deep learning | N29: Performance prediction is evaluated using Root Mean Squared Error (RMSE), while the classification of at-risk students is assessed through accuracy, recall, and F1-score. | O29: The proposed model achieved an average RMSE of 4,8 in predicting knowledge and skills (Table 7), alongside an accuracy of 87,3%, a recall of 84,6%, and an F1-score of 85,9% in classifying at-risk students (Table 4). | P29: The authors reported difficulties in modeling weak relationships and long-term dependencies, insufficient performance in assessing ethical literacy and moral judgment, and lower predictive accuracy in underrepresented groups, such as Nigerian students, due to small subgroup sample sizes. | Q29: Class imbalance | R29: The paper states "Not applicable" in the ethical approval section. It notes that the data are available from the corresponding author upon reasonable request, but does not detail specific compliance with data protection regulations such as the GDPR.
A30: Enhancing Student Graduation Prediction with Integrated Deep Learning under Data Constraints | B30: 10.3724/2096-7004.di.2025.0071 | C30: Son, Nguyen Thi Kim and Vinh, Tran Doan and Quynh, Nguyen Huu and Tao, Ngo Quoc and Hop, Dang Trong and Minh, Bui Tuan | D30: June 10, 2026 | E30: Scopus, Data Intelligence, SciEngine | F30: Vietnam | G30: The study delivers the AWG-GC model, a unified paradigm where an Autoencoder compresses high-dimensional sparse data, a WGAN generates synthetic samples to mitigate class imbalance, and a Graphormer utilizes global attention for relational classification. This architecture functions as a cohesive synergy rather than an ensemble, where representation learning directly informs the generative and classification phases. | H30: The total study population includes 5.246 students across three datasets: 551 from HNMU; 271 from VNU; 4424 from SATDAP. | I30: In-person | J30: HNMU/VNU (39–50 features): Specialized course GPAs, completed credits, instructor evaluations, and scientific research participation. SATDAP (36 features): Categorized into Demographics (age, gender, marital status, disability), Socio-economic (parents' education/occupation, student debt, scholarships), and Learning Journey (entrance scores, high school repetition years, field of study choice). | K30: Academic records, Demographic data | L30: The primary architecture is the AWG-GC—Autoencoder Wasserstein Generative Adversarial Network (WGAN) Graphormer Graduation Classification. Benchmarking included eight baseline classifiers: SVM, KNN, Random Forest (RF), GAT, Transformer, Graphormer (standalone), AutoGAT, and AWG-GAT. | M30: Deep learning | N30: Evaluation utilized classification metrics (Accuracy, Precision, Recall, F1-score, ROC-AUC), statistical validation (p-values via paired t-tests, 95% Confidence Intervals), and synthetic data validation (Fréchet Inception Distance - FID). | O30: AWG-GC achieved a peak F1-score of 99,25% (HNMU). The results were statistically significant with p < 0,001 compared to the Transformer baseline. ROC-AUC reached 0,989 for Vietnamese datasets and 0,911 for SATDAP. Tabela 2 (HNMU dataset): Accuracy 98,54, Precision 99,25, Recall 99,25, F1-Score 99,25, ROC-AUC 0,989. | P30: The authors identified high computational complexity due to the multi-layer integrated architecture, a lack of "Black Box" interpretability for academic stakeholders, and an overfitting risk if data augmentation rates exceed optimal thresholds. | Q30: Resource overhead, Result interpretability | R30: Ethics approval was marked as "Not applicable." The study lacks discussion on student data consent, GDPR compliance, or specific anonymization protocols.
A31: Academic Temporal Pattern Mining for Enhanced Student Performance Prediction: A Hybrid Machine Learning Approach | B31: 10.1109/ICDSAAI65575.2025.11011532 | C31: Rajendran, Vasanth and Besiahgari, Dinesh and Patil, Sachin Chandrakant and Challagulla, Vishnu and Chandrashekaraiah, Manjunath | D31: Date of Conference: 28-29 March 2025; Date Added to IEEE Xplore: 29 May 2025 | E31: IEEE Xplore, 2025 International Conference on Data Science, Agents & Artificial Intelligence (ICDSAAI), IEEE | F31: United States | G31: Develop a new Academic Temporal Pattern Mining (ATPM) framework that extracts time-series features from raw academic records. A hybrid machine learning ensemble (Random Forest + XGBoost), that leverages the strengths of both models. A demonstration of an early warning mechanism that can identify high-risk students at least three weeks before final assessments, with an 80% accuracy threshold. | H31: The dataset comprises 1.000 undergraduates across various degree programs. Primary data were sourced from the public UCI Student Performance Data Set and augmented with extended logs tracking student attendance and forum activity. To capture behavioral dynamics rather than relying on a static cross-sectional analysis, the dataset was structured into 12 weekly temporal windows. The initial ten windows were utilized for model training, whereas the final two windows were held out for model evaluation. | I31: Online | J31: Learning management system logs (partial/final grades), attendance records, demographic data, assessment results, and participation in academic forums. | K31: Academic records, Demographic data, VLE activity log | L31: Random Forest: Robust to noise and missing data, provides global and interpretable feature importance metrics; and XGBoost: Captures non-linear interactions and handles sparse data effectively, efficient implementation of gradient boosting, suitable for large or moderately complex datasets. Each model outputs an academic risk probability (the likelihood of a student exhibiting low performance or failing). | M31: Ensemble learning | N31: Accuracy, Precision, Recall, F1, and AUC (Area Under the ROC Curve). As well as paired t-test (p-value < 0,05) to confirm the statistical significance of the observed improvements. The hybrid model was compared with Logistic Regression, Random Forest alone, and XGBoost alone. | O31: Table 1, Figure 3: The hybrid approach achieved the highest accuracy (87%), representing a 15% improvement compared to Logistic Regression and a 6–7% improvement over the standalone models (p < 0,01). Figure 2: Precision improves as the system progresses through the semester's weekly windows. Table 2: Starting from Week 6, the system reaches the acceptable threshold of 80% precision (75% Recall) in risk prediction, achieving its best performance in Week 12 (87% Precision, 85% Recall). | P31: The authors acknowledged several key limitations in their study. First, missing data or low interaction logging frequencies can adversely affect model performance and elevate the risk of overfitting. Furthermore, because Learning Management System (LMS) usage patterns vary substantially across different academic courses, the model requires specific adjustments and fine-tuning rather than a universal approach. | Q31: Class imbalance, Model generalization, Privacy concerns | R31: The authors emphasize the critical need for alignment with data protection regulations—such as FERPA, GDPR, and LGPD—during data collection and processing. Furthermore, they argue that the stigma associated with the "at-risk student" label can negatively impact student morale. Consequently, comprehensive training for instructors who will utilize the tool is essential to ensure responsible and constructive implementation.
A32: A machine learning framework for soft skills assessment: Leveraging serious games in higher education | B32: 10.1016/j.caeai.2025.100469 | C32: Marengo, Agostino and Pagano, Alessandro and Santamato, Vito | D32: August 30, 2025 | E32: Scopus, Computers and Education: Artificial Intelligence, Elsevier | F32: Italy | G32: How can predictive machine learning algorithms, applied to soft skills data collected through serious games, identify the most suitable learning pathway for each student—thereby enhancing academic guidance and increasing the likelihood of educational success? | H32: The sample comprised 211 undergraduate students from an Italian university, enrolled in Business Administration, Sport and Exercise Sciences, and Modern Literature degree programs. All participants were attending a mandatory Computer Science course at the time of the study. | I32: In-person | J32: Transversal competencies (time management, priority management, and planning) were measured during a serious game session based on realistic management scenarios (correlation coefficient = 0,90). The gameplay was preceded by a questionnaire assessing demographic information (age, gender), academic indicators (term, major, GPA), and prior knowledge of serious games. Following the session, participants completed a game evaluation questionnaire (Cronbach alpha = 0,85) and the COTI-33 scale (alpha = 0,92) to evaluate technological factors, comfort, usability, and time perception. All questionnaires employed a 5-point Likert scale. Data preprocessing and model training were performed using Orange Data Mining. Outliers were detected and removed using the Local Outlier Factor (LOF) algorithm, configured with a 10% contamination rate and 20 neighbors. After cleaning, 193 valid instances remained, which were split into a training set (80%, n = 155) and a test set (20%, n = 38). | K32: Academic records, Demographic data, Multi-modal data | L32: Several machine learning models were evaluated and compared, including Logistic Regression, Neural Network, Support Vector Machine (SVM), Random Forest, Gradient Boosting, Naive Bayes, AdaBoost, and Stochastic Gradient Descent (SGD). Logistic Regression was selected for the study as it achieved the highest Area Under the Curve (AUC), alongside robust performance across other evaluation metrics. The statistical reliability of the model was confirmed through the Friedman test and subsequent Nemenyi post-hoc analysis, which yielded satisfactory results. | M32: Machine learning | N32: Model performance was evaluated using standard classification metrics derived from the confusion matrix: Area Under the Receiver Operating Characteristic Curve (AUC-ROC), Accuracy, Precision, Recall, F1-Score, and Matthews Correlation Coefficient (MCC). AUC-ROC served as the primary selection metric, as it provides a comprehensive and threshold-independent evaluation of the model's ability to discriminate between classes. | O32: The performance evaluation metrics are presented in Figures 3, 4, and 5—with Logistic Regression (Machine Learning) best performing. Feature importance and impact were examined using SHapley Additive exPlanations (SHAP). Grade Point Average (GPA) was identified as the most critical feature, exerting a substantial influence on the model's predictive power, whereas soft skills exhibited a lower relative impact. Finally, Data Envelopment Analysis (DEA) was performed to evaluate student efficiency in translating soft skills into academic achievement (GPA). | P32: The analysis of the results was specifically tailored to the characteristics of the three degree programs examined. The discussion highlighted correlations between soft skills and domain-specific requirements, thereby constraining the generalizability of these findings to other educational contexts. | Q32: Model generalization | R32: Participation in the study was restricted to students who signed the Informed Consent Form (ICF), explicitly agreeing to the data collection and privacy terms.
A33: Leveraging graph neural network for learner performance prediction | B33: 10.1016/j.eswa.2025.128724 | C33: Hakkal, Soukaina and Lahcen, Ayoub Ait | D33: June 23, 2025 | E33: Scopus, Expert Systems With Applications, Elsevier | F33: Morocco | G33: Recent approaches generally focus on specific datasets, making it difficult for models to generalize across different contexts. This highlights the need for a scalable, course-independent architecture that is adaptable to diverse educational settings. To address this challenge, the authors propose a flexible framework implementing multiple GNN variants—specifically Edge Classification and Representation Learning—to construct a comprehensive learning graph aimed at generalizing across five distinct real-world educational datasets. Furthermore, the GNN-generated embeddings are integrated into tree-based Ensemble Learning models, such as XGBoost and LightGBM. | H33: The Assistments (assist17 and assist09), Statics, Spanish, and Moodle-Morocco datasets represent five distinct educational contexts, respectively: a web-based tutoring system, an autumn 2011 Carnegie Mellon University Statics course, a high school Spanish class using the Colorado Optimized Language Tutor (COLT) system, and a Python course at the National School of Applied Sciences in Morocco. For evaluation, 70% of the data was allocated for training, 15% for validation, and 15% for testing. | I33: Hybrid | J33: Specifically, the datasets cover the following features: Assistments includes student response data, interaction timestamps, problem difficulty levels, and performance metrics; Statics involves mathematical methods used in solving engineering problems; Spanish utilizes a flashcard-based tool for language learning; and Moodle-Morocco contains student performance records categorized by skill level in multiple-choice questions. | K33: Academic records, VLE activity log | L33: Reproducibility across multiple execution runs is ensured using Python's random library, alongside setting explicit seeds for PyTorch and NumPy. The graph is initially constructed using the NetworkX library and subsequently converted into PyTorch Geometric (PyG) format, which is optimized for tensor operations and large-scale neural network training. Node attributes and edge labels are initialized using one-hot encoding to represent interaction correctness. To reduce memory overhead and computational complexity, subgraphs are randomly sampled to feed GNN architectures (SAGEConv, GCNConv, and GATConv) acting as feature extractors. Model training utilizes Focal Loss to target hard-to-classify examples, while the final integration with tree-based ensemble models (XGBoost and LightGBM) mitigates class imbalance. | M33: Ensemble learning | N33: Section 4.3, Step 9: AUC, accuracy, precision, recall, and F1-score. The metrics were evaluated across each dataset, and performance was compared between the standalone GNN baseline models and the combined GNN-Ensemble architectures. | O33: Table 3: The results demonstrate that GNN-based models combined with ensemble learning techniques yielded satisfactory performance, consistently outperforming the standalone GNN baseline model. Furthermore, these improvements remained consistent across all evaluated datasets, highlighting the proposed framework's ability to generalize across diverse educational contexts. | P33: The lower performance of GNNs on imbalanced datasets highlights the need for further refinement. While GNNs are effective at capturing graph structures, they often struggle to learn representations for minority classes without additional balancing techniques. | Q33: Class imbalance | R33: All datasets utilized were publicly available. However, ethical considerations, privacy concerns, and informed student consent were not explicitly addressed.
A34: Predicting Academic Success of College Students Using Machine Learning Techniques | B34: 10.3390/data9040060 | C34: Guanin-Fajardo, Jorge Humberto and Guaña-Moya, Javier and Casillas, Jorge | D34: April 22, 2024 | E34: Scopus, Data, MDPI | F34: Ecuador | G34: One of the study's primary objectives is to evaluate machine learning models in predicting academic performance. To this end, the authors compared the performance of nine models using the same dataset. Experimental results show that XGBoost achieved the best overall performance. However, the authors highlight that while the decision tree (C4.5) was less accurate than XGBoost, it provided greater practical utility by offering clear, readable rules for academic managers. | H34: Data were extracted from the academic management database of a university in Quevedo, Ecuador. The dataset was structured according to the courses taken by students during their first academic year, encompassing a total of 6.690 evaluated students and 286 selected instructors. | I34: In-person | J34: The collected student variables include degree program, enrolled courses, gender, age, high school type (public or private), geographic location, and university entrance exam score. | K34: Academic records, Demographic data | L34: The authors evaluated several predictive models, including XGBoost, Random Forest, GBM, Bagging, C4.5, Naive Bayes, SVM with Radial Basis Function kernel (SVM-RBF), SVM with Polynomial kernel, and Multi-Layer Perceptron (MLP). | M34: Ensemble learning | N34: Accuracy, Sensitivity (Recall), Specificity, AUC (Area Under the ROC Curve), Precision, Cohen's Kappa, and Log Loss. | O34: The evaluated predictive models were compared, with XGBoost demonstrating the highest performance: Accuracy = 0,7949, Recall = 0,8425, Precision = 0,8214, F1-score = 0,8306, and AUC = 0,8775. | P34: The authors note that the primary limitation of the study is the lack of metrics to evaluate the correlation between demographic variables and performance prediction, "as it is crucial to analyze fairness and bias in algorithmic decision-making when building predictive models". | Q34: Privacy concerns, Result interpretability | R34: The authors state that the students' personal information, including their specific degree program, was anonymized.
A35: Research on online learning behavior classification method based on LSTM and CNN | B35: 10.1145/3700297.3700314 | C35: Liu, Yijia and Isha bin Awang, Mohd and Zain, Farah binti Mohamad | D35: November 18, 2024 | E35: Scopus, ISAIE '24: Proceedings of the 2024 International Symposium on Artificial Intelligence for Education, ACM | F35: China | G35: Online learning—which has gained traction in recent years, particularly in the wake of the COVID-19 pandemic—presents new challenges and requires approaches distinct from those used in face-to-face instruction. In online education, students are responsible for managing their own study time, while instructors face difficulties in gauging student engagement, a scenario markedly different from the traditional classroom environment. Therefore, the authors propose an approach to classify student learning in online environments into three specific categories: active, passive, and irregular participation. To achieve this, they implemented a hybrid LSTM-CNN architecture to extract temporal features from behavioral and learning activity data prior to classifying the students. | H35: The experiment utilized a dataset from an undergraduate online course in Modern Logistics Management at a university in Guangdong, China. However, the total number of students in the dataset was not specified. | I35: Online | J35: Tables 1 and 2: The dataset contained daily records of student behaviors and activities. For the analysis, the data were organized chronologically and divided between the models. The LSTM network received the temporal behavioral data inputs, including the duration and number of videos watched, forum interactions (replies and posts), the number of submitted assignments, login frequency, and total study time. The CNN was used to extract performance features from a matrix composed of assignment and exam grades. Unique student identifiers and timestamps were primarily used to structure and sequence these time series. | K35: Academic records, VLE activity log | L35: The study employed a hybrid approach combining two deep learning models: LSTM and CNN for feature extraction across different data modalities. Specifically, the LSTM captures temporal behavioral patterns, whereas the CNN extracts performance patterns from academic activities. The features extracted by both models are subsequently fused and processed by an MLP classifier, which performs the final classification of students into active, passive, or irregular participation categories. | M35: Deep learning | N35: Accuracy, Precision, Recall, F1-Score: The proposed model was evaluated against conventional classification baselines, including Decision Trees, Support Vector Machines, Random Forests, and K-Nearest Neighbors. It was also compared to other deep learning architectures, such as standalone GRU and standalone LSTM models. | O35: Table 3: The proposed model outperformed all baseline approaches across all evaluated metrics, achieving an accuracy of 95,2%, precision of 94,2%, recall of 93,6%, and an F1-score of 93,8%. | P35: The authors report that, although the proposed model demonstrated promising results, it encountered difficulties in classifying students with "irregular participation." Consequently, they suggest incorporating additional contextual features in future research to enhance classification performance. | Q35: Class imbalance, Data availability | R35: The authors did not address data privacy and protection concerns, nor did they mention whether informed consent was obtained from the students included in the dataset.
A36: Integrating Expert Knowledge with Automated Knowledge Component Extraction for Student Modeling | B36: 10.1145/3699682.3728348 | C36: Sampaio De Alencar, Rafaella and Demirtas, Mehmet Arif and Saha, Adittya Soukarjya and Shi, Yang and Brusilovsky, Peter | D36: July 13, 2025 | E36: Scopus, UMAP '25: Proceedings of the 33rd ACM Conference on User Modeling, Adaptation and Personalization, ACM | F36: United States | G36: Knowledge Components (KCs) model learning at the level of individual concepts and skills. In programming, these components may represent specific knowledge regarding loops, variable types, data structures, and related concepts. In this context, this study proposes a hybrid approach that integrates the semantic precision of expert-built ontologies—which ensure high interpretability—with automated modeling to achieve superior statistical fit. Modeling the student's knowledge components extracted from various programming activities can reveal the development of student learning over time. Research Question: How do student models using ontology-based KCs compare to those using AST-based KCs in terms of fit and predictive power while maintaining interpretability? | H36: The dataset used contained questions from activities in an introductory Java programming course at a US university. It comprises 50 programming exercises divided into 5 assignments of 10 questions each, covering conditionals, logical operations, loops, and arrays. Although the dataset includes records from 400 students, the authors selected a random sample of 100 students, primarily due to processing power constraints. Only the students' first attempts at each exercise were considered, as students corrected their errors in subsequent attempts. Furthermore, only syntactically valid submissions were included, as lexical analysis of components could fail on invalid code, and without an Abstract Syntax Tree (AST), the system cannot identify which concepts the student was attempting to apply. | I36: In-person | J36: For each programming exercise, knowledge components (KCs) were extracted corresponding to the specific skills students applied in their solution code. | K36: Knowledge component | L36: The research integrates a Java ontology—comprising semantically relevant concepts defined by experts—with automated extraction of Knowledge Components (KCs) based on Abstract Syntax Trees (ASTs). It employs the JavaParser tool to map low-level AST nodes to the semantic categories of the ontology. Through this approach, the model seeks to address the challenge of balancing the interpretability of domain expertise with statistical fit and the scalability of automated processing. | M36: Machine learning | N36: The conventional AST-based model for KC extraction was compared against the proposed hybrid model. Learning curves were plotted visually (Figure 2). The Root Mean Squared Error (RMSE) metric and the Bayesian Information Criterion (BIC) were used to evaluate model fit relative to a baseline reference. Generally, lower BIC values indicate a superior model fit. | O36: Figure 2: The ontology-based model exhibits a steeper learning curve slope compared to the AST-based model, indicating a superior model fit. Table 1: The hybrid model yielded lower RMSE values when predicting error rates for new students across new opportunities (0,318) and new problems (0,315), both outperforming conventional models. Furthermore, the proposed model achieved a substantial reduction in BIC compared to the baseline model. Therefore, the combined results from the learning curves, BIC, and RMSE directly answer the research question, demonstrating that the ontology-based hybrid model achieves higher goodness of fit and predictive power than its AST-based counterpart. | P36: The authors state that this study is preliminary and was therefore validated on only a single dataset. They suggest expanding the dataset in future experiments. | Q36: Model generalization | R36: The dataset used was anonymized for ethical reasons; no personal information or academic performance data was made publicly available.
A37: Revolutionizing Departmental Management through Intelligent Technology:A Machine Learning Approach to Optimization | B37: 10.1109/AIMLA63829.2025.11040379 | C37: Arockia Mary, P. and Umamaheswari, K. and Bhushan, S.S. and Hariharan, K.S. and Dennish Albert, G. and Harivarshan, R. | D37: Date of Conference: 29-30 April 2025; Date Added to IEEE Xplore: 27 June 2025 | E37: Scopus, 2025 3rd International Conference on Artificial Intelligence and Machine Learning Applications Theme: Healthcare and Internet of Things (AIMLA), IEEE | F37: India | G37: The authors propose an academic management system powered by artificial intelligence. Figure 1: Functionalities include automatic class scheduling, test question generation, student career management, resource and event organization, as well as student attendance and academic performance analysis. The system is protected by user authentication, including the definition of permissions for specific groups. From the visual interface, among the application's various modules, the user has access to the academic performance prediction and analysis module. | H37: The size of the dataset used to evaluate the system's performance was not specified. However, the monitored data are collected by a system module and are stored in a database, such that proper precautions for sensitive data protection were taken, such as Role-Based Access Control (RBAC), Multi-Factor Authentication (MFA), and AES-256 encryption, as well as anomaly detection mechanisms. | I37: In-person | J37: The data collection module extracts structured and unstructured data from multiple academic sources, including faculty schedules, student attendance records, academic performance records, placement tracking data, and event participation records. For the academic performance prediction module, the predicted grade is calculated from attendance history, assignment and homework records, and prior academic performance in terms of course results (or grades). | K37: Academic records | L37: It employs a Long Short-Term Memory (LSTM) neural network (Deep Learning) to process students' historical academic records and predict their academic performance. | M37: Deep learning | N37: Due to the broad range of modules in the proposed system, the evaluation of the academic performance prediction module was described only briefly. The primary metric assessed was predictive accuracy, which was benchmarked against traditional regression-based models. | O37: The student performance prediction module achieved 96% accuracy, yielding a 20% improvement in the early identification of at-risk students compared to baseline methods. | P37: The study primarily highlights the key advancements of the proposed system, particularly in the Related Work section, where the authors contrast the limitations of existing literature with their approach. | R37: The sample size of the dataset used to evaluate the system was not specified, nor was the informed consent of the students. However, the system addresses ethics and data protection issues by describing the steps used to protect students' sensitive information in the database.
A38: GPAformer: A Transformer-Based Framework for Predictive Academic Performance Modeling and Real-Time Intervention in Undergraduate education | B38: 10.1145/3775073.3775153 | C38: Wan, Mai | D38: December 10, 2025 | E38: ACM Digital Library, ISAIE '25: Proceedings of the 2025 2nd International Symposium on Artificial Intelligence for Education, ACM | F38: China | G38: The authors highlight key gaps in the literature regarding academic performance prediction. Specifically, existing models struggle to adapt to heterogeneous student data over long periods, offering low flexibility in the face of evolving learning patterns, courses, and academic contexts. Furthermore, these studies fail to provide a practical framework compatible with the sparse and incomplete nature of educational datasets. To address these challenges, the authors propose the GPAformer framework, which effectively predicts academic outcomes based on student behavior patterns inferred through a Transformer-based architecture. The proposed framework mitigates dataset noise using a self-attention mechanism and establishes an operational, real-time intervention system driven by an automated threshold-based triggering mechanism. | H38: The dataset was collected from an undergraduate Information Systems program, comprising records from 500 students across a four-year period. The data was split into 80% for training and 20% for evaluation. The model was implemented in PyTorch and trained using the Adam optimizer. | I38: In-person | J38: Students' academic transcripts—specifically their course grades—are modeled as a temporal sequence that feeds into a Transformer-based model to predict future GPA. | K38: Academic records | L38: The authors frame the problem as evaluating students' academic transcripts to infer future performance. To this end, they implement GPAformer—a neural network architecture adapted from the Transformer model—which takes a student's performance as a temporal sequence and predicts their future GPA. | M38: Deep learning | N38: The prediction model was evaluated using Mean Absolute Error (MAE) and the coefficient of determination (R-squared). | O38: The proposed model was compared against LSTM and CNN baselines, achieving Mean Absolute Error reductions of 12,8% and 16,7%, respectively (reaching 0,103 for GPAformer). Overall, the proposed model achieved an R-squared of 0,9994, significantly outperforming the baseline models. A visual comparison of model performance is presented in Figure 2. | P38: The authors note no specific limitations of their model; however, future work aims to extend the approach by evaluating the longitudinal impact of academic performance prediction on student learning outcomes. | R38: The authors do not discuss ethics or privacy implications, nor do they mention obtaining informed consent from the students whose data comprised the dataset.
A39: AI-Based Student Performance Prediction using Machine Learning Techniques | B39: 10.1109/GSEACT68539.2026.11620534 | C39: Nagrale, Akshit and Karande, Aarti | D39: Date of Conference: 12-13 June 2026; Date Added to IEEE Xplore: 07 August 2026 | E39: IEEE Xplore, 2026 IEEE Global Symposium on Emerging and Communication Technologies (GSEACT), IEEE | F39: India | G39: Development of an AI-based prediction framework and a critical Feature Importance Analysis which identified prior academic grades (G1, G2), study time, and attendance as the primary predictors of success. The study explicitly seeks to create a predictive model to classify students into performance categories (High, Medium, Low) and identify at-risk individuals for early intervention. | H39: While the exact row count (n) is not explicitly stated, the study utilizes the UCI "Student Performance Dataset" and relevant Kaggle student performance datasets. The methodology is transparent, detailing mean/median/mode imputation, "One Hot Encoding" for categorical variables, and "Standard Scaler" for feature normalization, alongside a standard 80/20 train-test split. The research utilizes open-source benchmark datasets (UCI "Student Performance Dataset" and Kaggle), which include records from varied secondary and higher education contexts, suggesting broad applicability. | I39: In-person | J39: Demographic: Age, gender, family background; Academic: Past grades (G1, G2), study time, attendance records; Behavioral: Extracurricular participation, internet usage, and family support. | K39: Academic records, Demographic data | L39: Decision Tree (DT), Random Forest (RF), Support Vector Machine (SVM), and Extreme Gradient Boosting (XGBoost). | M39: Ensemble learning | N39: Accuracy. | O39: XGBoost (Ensemble Learning, 91%), Random Forest (88%), SVM (85%), and Decision Tree (82%). | P39: Data privacy concerns, lack of model interpretability (Explainable AI needs), and class imbalance in educational data. | Q39: Class imbalance, Privacy concerns, Result interpretability | R39: Detailed mentions of GDPR and FERPA compliance; requirements for anonymization and secure data storage.
A40: Optimizing Student Engagement Prediction with Machine Learning and Big Data Analytics | B40: 10.1109/ICMCTC62214.2025.11196115 | C40: Prince Mary, S. and Gambhir, Vinima and Mahalakshmi, R. and Begum, Benazeer and Kala and Mahajan, Shriya | D40: Date of Conference: 10-11 April 2025; Date Added to IEEE Xplore: 17 October 2025 | E40: Scopus, 2025 International Conference on Metaverse and Current Trends in Computing (ICMCTC), IEEE | F40: India | G40: This study implements a Shark Nose Optimizer-tuned Dynamic Support Vector Regression (SNO-DSVR) approach combined with big data analytics to predict student engagement levels from academic and behavioral data. Figure 1: Data extracted from an educational dataset undergo Min-Max normalization preprocessing, followed by feature extraction via Principal Component Analysis (PCA). Student engagement is then predicted using the proposed SNO-DSVR model, and performance metrics are evaluated. | H40: The dataset was obtained from Kaggle. Min-Max normalization was applied to scale all monitored variables to the range [0, 1], thereby removing scale bias. Subsequently, dimensionality reduction was performed using Principal Component Analysis (PCA), which transforms the original features into principal components. This process captures maximum variance and hidden patterns while eliminating redundant features and enhancing interpretability. By isolating the most significant information, PCA improves both predictive power and model performance. | I40: In-person | J40: The dataset includes demographic attributes: unique student identifier, age, gender, and high school type (prior to graduation). Socioeconomic information: details about scholarships, engagement in additional work, and means of transportation. Extracurricular activities: participation in sports activities and weekly study hours. Academic behavior: attendance records. Specific performance measures: evaluations in areas such as reading, note-taking, classroom attention, and contribution to projects. As well as final grades, which are used as the target variable for the analysis. | K40: Academic records, Demographic data | L40: The SNO-DSVR framework integrates the hyperparameter optimization capability of the Shark Nose Optimizer (SNO), with Dynamic Support Vector Regression (DSVR) to enhance student engagement prediction accuracy. This hybrid approach fine-tunes the model's hyperparameters, ensuring superior performance in educational data analytics. Support Vector Machines (SVM) serve as a supervised learning paradigm for regression and classification by constructing an optimal hyperplane within the feature space to delineate data points. In this study, both Support Vector Regression (SVR) and Support Vector Classification (SVC) variants are implemented. The optimal parameter configuration is determined via the SNO algorithm, achieving the highest fitness score through k-fold cross-validation. This process dynamically refines the DSVR model, yielding globally optimal performance and minimizing prediction errors. | M40: Machine learning | N40: The proposed model (SNO-DSVR) was evaluated against baseline models (LightGBM and CatBoost) across key performance metrics, including AUC, Log Loss, Recall, Accuracy, and Precision. | O40: The proposed model presented superior results to those of the baseline models (Table 1): AUC 97%, Log Loss 21,4%, Recall 94,12%, Accuracy 93,15%, and Precision 95%. | P40: The authors report that the scope is limited to a single dataset, which affects the model's generalization. Future work may integrate other datasets, information collected in real time, and improvements in the model's scalability and interpretability. | Q40: Model generalization | R40: The authors do not address ethical considerations and data privacy concerns, nor do they mention informed consent protocols for the students included in the dataset.
A41: Hybrid Machine Learning Approach for Classification and Recommendation of EDM | B41: 10.1109/IIPEM65914.2025.11548244 | C41: Khasne, Mukul V and Arjariya, Tripti | D41: Date of Conference: 25-25 November 2025; Date Added to IEEE Xplore: 09 June 2026 | E41: Scopus, 2nd International Conference on Intelligent and Innovative Practices in Engineering & Management (IIPEM) 2025, IEEE | F41: India | G41: The primary contribution of this study is the development of a Hybrid Machine Learning (HML) framework that integrates supervised, unsupervised, and deep learning techniques to enhance classification and recommendation tasks in Educational Data Mining (EDM). Specifically, the authors proposed an RNN-SVM hybrid model that combines the sequential pattern learning of Recurrent Neural Networks (RNNs) with the robust classification capability of Support Vector Machines (SVMs) to predict student performance levels, learning preferences, and dropout risks. Additionally, the study introduces a hybrid recommendation system leveraging a Neural Collaborative Filtering (NCF) architecture—which merges matrix factorization and deep neural networks—to provide highly tailored and personalized learning materials based on historical interaction data and preferences. | H41: The target paper does not explicitly report or define the exact sample size, number of student records, or total instances in the dataset used for model validation. The authors limit their description to stating that the framework's validation was conducted using "real-world educational datasets" obtained from academic institutions and online learning platforms, but they completely omit any quantitative details regarding dataset size or record counts. | I41: Hybrid | J41: The attributes and variables monitored and utilized by the model are categorized into academic, behavioral, and demographic indicators, which include exam scores, attendance records, learning preferences, demographic details, prior academic records, extracurricular activity involvement, and other unspecified external factors that impact learning outcomes. | K41: Academic records, Demographic data | L41: The study implements and evaluates several classification and prediction models, which include traditional baseline algorithms such as Support Vector Machines (SVM), K-Nearest Neighbors (KNN), ID3, C4.5, and Random Forest, along with a Recurrent Neural Network (RNN) and the proposed Hybrid Machine Learning (HML) model. Furthermore, a Neural Collaborative Filtering (NCF) architecture is applied for recommendation tasks, and an Autoencoder (LAE) is utilized to achieve dimensionality reduction. | M41: Machine learning | N41: The classification and prediction models are evaluated using accuracy, precision, recall, F1-score, and Mean Absolute Error (MAE), while the performance of the recommendation system is assessed using Mean Reciprocal Rank (MRR) and Root Mean Square Error (RMSE). Additionally, model stability and robustness are analyzed across fivefold, tenfold, and fifteenfold cross-validation scenarios using confusion matrix analysis. | O41: Quantitatively, the experimental results demonstrate that the proposed HML classifier outperforms all other models, achieving the highest performance across all evaluated metrics with an accuracy of 97,8%, precision of 97,5%, recall of 97,9%, and F1-score of 97,7%. | P41: The authors report several model-specific limitations, noting that the Random Forest model, despite its robustness, is computationally expensive compared to other approaches; ID3 and C4.5 decision trees are prone to overfitting on complex and high-dimensional datasets; and K-Nearest Neighbors (KNN) is highly susceptible to noise and requires meticulous parameter tuning of the "K" value to prevent misclassification. Furthermore, they highlight that traditional machine learning algorithms struggle to deal with missing values, sparse data, and the dynamic nature of educational environments, while conventional recommendation engines are heavily constrained by cold-start and sparsity issues. | Q41: Class imbalance, Data availability, Resource overhead | R41: The study does not address, analyze, or report any ethical or privacy issues associated with educational data mining.
A42: Leveraging machine learning and clickstream data to improve student performance prediction in virtual learning environments | B42: 10.1108/IDD-08-2024-0120 | C42: Khoudi, Zakaria and Hafidi, Nasreddine and Nachaoui, Mourad and Lyaqini, Soufiane | D42: January 30, 2025 | E42: Web of Science, Information Discovery and Delivery, Emeral Publishing Limited | F42: Morocco | G42: The purpose of the research is to evaluate the usefulness of clickstream data and machine learning algorithms to predict student performance accurately, aiming to allow early interventions and reduce failure and dropout rates in virtual environments. | H42: 5.372 students (after preprocessing that removed dropout students and consolidated the data for the Social Sciences course "BBB"). | I42: Online | J42: The analysis primarily focuses on VLE clickstream data, which captures student interactions across 12 distinct activity types: homepage, forumng (discussion forums), subpage, oucontent, resource, quiz, url, glossary, sharedsubpage, ouelluminate, oucollaborate, and questionnaire. | K42: VLE activity log | L42: The article implements traditional baseline models—including Logistic Regression (LR), Naive Bayes (NB), K-Nearest Neighbors (KNN), Random Forest (RF), and XGBoost—alongside advanced time-series architectures such as LSTM-XGBoost and Gated Recurrent Units (GRU). | M42: Deep learning | N42: Model performance was evaluated using standard classification metrics: Accuracy, Precision, Recall, F1-Score, and Area Under the Receiver Operating Characteristic Curve (AUC-ROC). | O42: The GRU model (Deep Learning) achieved the highest performance, reaching an accuracy of 90,1%, precision of 90,8%, recall of 96,0%, F1-score of 93,3%, and an AUC-ROC of 86,0%. | P42: The authors acknowledge that the analysis was centered on a single course ("BBB"), which may limit the application of the results to other contexts; the implementation and maintenance of advanced models require technical expertise that some institutions may not possess; and the study focused on short- to medium-term predictions. | Q42: Model generalization, Resource overhead | R42: The study used a dataset that underwent a rigorous anonymization process to ensure that individual students were not identified. The authors also discuss the need for bias audits to ensure that the models do not harm specific groups (ethnicity, gender, etc.).
A43: Teaching innovation mechanism of higher education driven by AI fusion data | B43: 10.1007/s10791-026-10036-w | C43: Chen, Zhen and Qin, Shirong and Han, Hui and Peng, Wei and Liang, Hua | D43: March 17, 2026 | E43: Springer Link, Discover Computing, Springer Nature | F43: China | G43: This study proposes an educational environment powered by the integration and AI processing of multimodal data, enabling real-time instructor support and personalized learning pathways for students. The approach was validated by comparing performance metrics between an experimental and a control group, demonstrating a 93% pass rate and a 74,8% knowledge retention rate. Furthermore, the average time required for pedagogical interventions dropped to 2,3 days—a 69,7% improvement. Crucially, the intervention yielded the highest impact among at-risk students compared to high achievers, effectively narrowing the learning gap. | H43: The data were obtained from a multimodal data collection ecosystem based on the integration of the student management system, the online learning platform, the in-person classroom environment, and an external resource library. So that the collected data are synchronized in real-time by the API of the proposed system's database module. The experimentation considered a sample of students in Computer Science and Technology and Electronic Information, from two universities in eastern China, containing records of 612 students across 12 required courses in the spring semester, totaling 18 academic weeks. | I43: Hybrid | J43: The proposed model analyzes students' cognitive, engagement, emotional, and environmental variables, as well as integrates covariates of prior academic performance, attendance rate, and frequency of learning behavior. Finally, it evaluates performance across multiple subjects, task scores, and the learning trajectory. | K43: Academic records, Demographic data, VLE activity log | L43: The authors describe a method for automatic diagnosis of students' knowledge gaps using the Bidirectional Long and Short-Term Memory (Bi-LSTM) model. The cognitive behavior and participation characteristics are processed using a Bidirectional Gated Recurrent Unit (BiGRU) neural network to capture long-term dependencies. 1D-Convolutional Neural Network (CNN) is implemented to extract semantic patterns from unstructured emotional features. Softmax normalization calculates the attention weight for each evaluated feature, as well as Temporal Attention Pooling to weight which time windows are most critical for prediction. Finishing, the result is processed by a fully connected network using a Sigmoid function to generate the risk probability. | M43: Deep learning | N43: The proposed system was evaluated based on both predictive model performance and its pedagogical impact on student learning. Model efficacy was measured using standard evaluation metrics, including ROC-AUC and F1-Score. | O43: The proposed Deep Learning model (KG-BERT) achieved an ROC-AUC of 0,912 and an F1-Score of 0,823, representing improvements of 17,1% and 34,5%, respectively, over the baseline models. | P43: The authors acknowledge several limitations, including the restriction of their evaluation to three specific undergraduate programs and the barrier posed by high implementation costs. Additionally, they highlight concerns regarding the model's adaptability to evolving student learning patterns over time (i.e., concept drift). Finally, the authors address ethical implications, noting that automated alerts and recommendations could inadvertently reinforce existing biases, thereby compromising educational equity. | Q43: Model generalization, Privacy concerns | R43: The authors note that all collected data were anonymized and outline a data isolation (sandboxing) mechanism designed to comply with data privacy and protection requirements.
A44: Educational data mining to support identification and prevention of academic retention and dropout: a case study in introductory programming | B44: 10.5753/rbie.2022.2518 | C44: Carneiro, Murillo Guimarães and Dutra, Bruna Luiza and Paiva, José Gustavo S. and Gabriel, Paulo Henrique Ribeiro and Araújo, Rafael Dias | D44: September 27, 2022 | E44: SBC OpenLib, Revista Brasileira de Informática na Educação, SBC | F44: Brazil | G44: The study contributes a dual-phase framework that first identifies at-risk students using predictive modeling (RQ1) and subsequently implements targeted pedagogical interventions, such as tutoring, programming contests, and supplementary content, to reduce retention rates (RQ2). | H44: The initial predictive modeling utilized 98 student records spanning the 2015–2017 period; subsequent evaluation phases involved cohorts of 79 students in 2018 and 73 students in 2019 during the intervention implementation. | I44: In-person | J44: The researchers monitored variables that represent a holistic student profile, including socio-economic factors (family per capita income, race, work situation), demographic data (age, gender, distance from university), and academic indicators (math average in high school, high school type). | K44: Academic records, Demographic data | L44: The study evaluated six machine learning algorithms: k-nearest neighbors (KNN), Decision Tree (J48), Random Forest (RF), Naive Bayes (NB), Multilayer Perceptron (MLP), and Pruning-based rule induction (JRIP). | M44: Machine learning | N44: Validation was performed using Accuracy and the F1 measure to account for class imbalance, supported by the McNemar statistical test for comparative error rate analysis between classifiers. | O44: The JRIP algorithm achieved a quantitative accuracy of 81,63%, with an 80,70% F1-score. Furthermore, the pedagogical interventions led to a statistically significant increase in success rates compared to previous years, evaluated at a 90% confidence level (p-value = 0,09, α = 0,1). | P44: The primary barriers reported include the highly unbalanced nature of the classes (69 failed vs. 29 passed) and the small database size, which challenged algorithms like Random Forest that typically require more balanced representation to avoid majority class bias. | Q44: Class imbalance, Data availability | R44: The research adhered to institutional guidelines through approval from the Research Ethics Committee under CAAE 86758718.0.0000.5152, ensuring oversight of student data usage.
A45: Predição de Evasão por meio de um Instrumento Sistemático de Avaliação Institucional | B45: 10.5753/wapla.2023.236179 | C45: Oliveira, Ronei and Medeiros, Francisco and Alves, Kamila | D45: November 6, 2023 | E45: SBC OpenLib, 2023: Anais do II Workshop de Aplicações Práticas de Learning Analytics em Instituições de Ensino no Brasil, SBC | F45: Brazil | G45: The research validates the use of existing, mandatory institutional assessment surveys as a high-fidelity data source for dropout prediction. Its primary contribution is demonstrating that subjective student self-evaluations and perceptions of teacher/course quality can be transformed into predictive features, achieving an F1-score of 91,57% without requiring the collection of additional sensitive socioeconomic data. | H45: The initial raw dataset consisted of 1.156.891 records. After filtering for student status (concluded or cancelled) and limiting the temporal scope to admissions from 2017 onwards, the data was reduced to 128.235 records. Following outlier removal and averaging, the final treated sample size used for model training and testing was 6.138 atomic records. | I45: In-person | J45: The model monitors 31 variables across four dimensions: Student (self-performance, motivation, commitment), Discipline (importance, difficulty), Teacher (clarity, fulfillment of plans, availability), and Course (recommendation probability, interest in leaving). Academic performance metrics, including final averages, attendance (failures), and the number of semester deferrals, were also integrated. | K45: Academic records | L45: The study evaluated three classification algorithms: Support Vector Machine (SVM), Random Forest (RF), and Decision Tree (DT). | M45: Ensemble learning | N45: The models were evaluated using Accuracy, Precision, Recall, and F-Measure (F1-Score). | O45: The proposed Random Forest + SMOTE model achieved an accuracy of 87,97%, precision of 91,72%, recall of 91,67%, and an F1-score of 91,57%. When deployed on active students admitted since 2017, the model identified a dropout potential in 59% of the population (13.310 out of 22.560 students). This 59% figure is consistent with UFPB’s historical dropout range of 51–60% observed between 2010 and 2018. | P45: Major barriers include the loss of temporal data due to system migrations and the exclusion of pre-2017 cohorts. A significant methodological constraint is the use of the "atomic life average," where a student's entire academic history is compressed into a single mean record; this results in a loss of temporal granularity, preventing the model from detecting semester-by-semester trends or sudden declines in performance. The lack of socioeconomic data is also cited as a limitation for further model enrichment. | Q45: Class imbalance | R45: Ethics are addressed through the use of an "anonymous" institutional evaluation system where data is treated at an aggregate or "atomic" level. The research was conducted within the institutional framework of the university's internal evaluation process, intended to facilitate pedagogical intervention and management rather than individual student surveillance.
A46: Modelo de Predição de Evasão Escolar com Base em Dados de Autoavaliação de Cursos de Graduação | B46: 10.5753/rbie.2024.3542 | C46: Oliveira, Ronei and Medeiros, Francisco | D46: September 1, 2024 | E46: SBC OpenLib, Revista Brasileira de Informática na Educação, SBC | F46: Brazil | G46: Consistent with the previous study (Oliveira et al., 2023). | H46: Consistent with the previous study (Oliveira et al., 2023). | I46: In-person | J46: Consistent with the previous study (Oliveira et al., 2023). | K46: Academic records, Demographic data | L46: Consistent with the previous study (Oliveira et al., 2023). | M46: Ensemble learning | N46: Consistent with the previous study (Oliveira et al., 2023). | O46: Consistent with the previous study (Oliveira et al., 2023). | P46: Consistent with the previous study (Oliveira et al., 2023). | Q46: Class imbalance | R46: Consistent with the previous study (Oliveira et al., 2023).
A47: Análise de Sobrevivência: um estudo de caso em um Curso de Sistemas de Informação | B47: 10.5753/wei.2022.223357 | C47: Souza, Joubert and Komati, Karin and Andrade, Jefferson | D47: July 31, 2022 | E47: SBC OpenLib, 2022: Anais do XXX Workshop sobre Educação em Computação, SBC | F47: Brazil | G47: The primary contribution of the study is the methodological integration of non-parametric survival analysis with machine learning classifiers to determine both the "when" and "why" of student attrition. By applying this dual approach, the authors contribute a verified framework for identifying that the highest risk of dropout occurs within the first two semesters, while simultaneously isolating the specific curriculum components that serve as the most significant academic barriers. | H47: The study leverages a robust dataset consisting of 1.169 unique student records. This sample size is statistically significant for a single-course case study, as it represents the total population of students enrolled in the Information Systems degree program over a thirteen-year period, providing a dense historical record of academic outcomes. | I47: In-person | J47: The researchers utilized a total of 202 features, categorizing data into demographic attributes—such as age, gender, and color—and granular academic history variables. Crucially, the academic features distinguish between different types of failure, specifically separating "failure due to grades" from "failure due to attendance", which the authors highlight as distinct and critical indicators of student engagement and dropout behavior. | K47: Academic records, Demographic data | L47: The study employs a multi-model approach, utilizing the non-parametric Kaplan-Meier estimator for survival analysis specifically because the theoretical distribution of the student data was "unknown" (Section 1). In addition to survival modeling, the authors applied three machine learning classifiers—Decision Trees, Gradient Boosting (GB), and XGBoost—to evaluate feature importance and predict student status (concluded, dropped out, or active). | M47: Ensemble learning | N47: The primary performance metric evaluated was accuracy, which signifies the proportion of correct predictions regarding student outcomes. The models demonstrated high reliability, with the Decision Tree achieving 88,46% accuracy, while both the Gradient Boosting and XGBoost models achieved superior results of 90,59%. | O47: The quantitative results reveal a severe "mortality" rate in the early stages of the program, with approximately 50% of total dropouts occurring within the first two semesters. Qualitatively, the models identified "Programming I" (CSI 002) and "Programming II" (CSI 009) as the primary academic barriers, indicating that success in these specific introductory modules is the most critical determinant of long-term student retention. | P47: The authors report significant limitations, including the necessary exclusion of academic data from 2020 and 2021 to eliminate the confounding effects of the COVID-19 pandemic. Furthermore, the researchers acknowledge that their reliance on institutional databases excludes external social, motivational, and financial factors, a research gap they explicitly link to the broader findings of the Hellas et al. (2018) systematic review. | Q47: Data availability | R47: Ethical concerns were addressed through the use of a dataset that was anonymized prior to researcher access. This protocol ensured that individual student identities were protected throughout the analysis of real academic records, adhering to institutional research standards at the Instituto Federal do Espírito Santo (IFES).
A48: Análise Comparativa entre Métodos Tradicionais de Aprendizado de Máquina e Aprendizado Ativo na Predição da Evasão Escolar | B48: 10.5753/wapla.2025.15898 | C48: Araújo, Felipe and Cabral, Luciano and Mello, Rafael | D48: November 25, 2025 | E48: SBC OpenLib, Anais do III Workshop de Aplicações Práticas de Learning Analytics e Inteligência Artificial no Brasil (WAPLA 2025), XIV Congresso Brasileiro de Informática na Educação (CBIE 2025), SBC | F48: Brazil | G48: The study provides a comparative analysis of two automated pipelines—traditional supervised learning and active learning—demonstrating that active learning can achieve competitive dropout prediction performance while significantly reducing the human effort required for data labeling. | H48: 4.424 student records. | I48: In-person | J48: The study monitors 35 independent variables categorized into demographic, academic, socioeconomic, and macroeconomic factors, utilizing a binarized target variable to distinguish between student dropout and retention/graduation. | K48: Academic records, Demographic data | L48: The traditional pipeline evaluated a total of eight supervised classifiers, including XGBoost, Random Forest, and LightGBM, with tuning performed via Optuna, BayesSearchCV, Grid Search, and Random Search; the active learning pipeline utilized a Random Forest base with sampling strategies including Entropy, Margin, Query by Committee (QBC), random sampling, and a hybrid uncertainty + diversity approach via KMeans. | M48: Ensemble learning | N48: Model performance was assessed using Accuracy, Precision, Recall, F1-Score, AUC-ROC, and Cohen’s Kappa. | O48: The traditional XGBoost model achieved a peak accuracy of 87,04%, while the active learning pipeline (Random Forest) reached a superior recall of 77,46% and an AUC-ROC of 90,00% using only 40% of the labeled data (with a textual reference in the study suggesting effectiveness with as little as 30% labels). | P48: Identified barriers include the potential bias introduced by the initial random seed in active learning, the exclusion of critical motivational and psychosocial variables, and the institutional specificity of the data, which limits broader generalizability. | Q48: Class imbalance, Model generalization | R48: The authors address ethical concerns through the lens of algorithmic fairness and equity in educational prediction, though the use of secondary Kaggle data limits the discussion regarding primary student consent protocols and real-time data protection.
A49: Análise dos principais fatores que influenciam a evasão no ensino superior utilizando técnicas de mineração de dados educacionais | B49: 10.5753/wei.2024.3105 | C49: Correia, Ronaldo and Mendonça, Harrison and Silva, Camila and Toledo, Douglas | D49: July 21, 2024 | E49: SBC OpenLib, 2024: Anais do XXXII Workshop sobre Educação em Computação, SBC | F49: Brazil | G49: The study contributes a structured, iterative predictive methodology utilizing the SelectKBest method for optimized feature selection and the identification of primary dropout factors in distance learning (EAD), ranging from specific academic discipline performance to socioeconomic profiles. | H49: The research utilized two primary datasets: Dataset 1 (Enrollment) with 132.763 records and Dataset 2 (History) with 430.561 records. For the predictive modeling phase, a balanced subset of 20.046 students (10.023 per class) was used. | I49: Online | J49: Variables include socioeconomic attributes (family/individual income, parents' education, age, gender, ethnicity, marital status, professional activity) and academic attributes (discipline codes, final grades, frequency, course code, and entrance exam/admission scores). | K49: Academic records, Demographic data | L49: XGBoost, Logistic Regression, Decision Tree (DT), Random Forest (RF), and Support Vector Machine (SVM). | M49: Ensemble learning | N49: Accuracy (AC), Precision (PR), and Recall (RE). | O49: The study achieved a maximum general accuracy of 92% using the XGBoost algorithm. Remarkably, this high performance was achieved using less than 20% of the available data characteristics (99 out of 566 features) as identified through the iterative SelectKBest process. | P49: Key challenges include the lack of standardization in historical socioeconomic questionnaires, the current absence of student interaction data from the Virtual Learning Environment (VLE), and the potential influence of course-specific dropout rates on the ranking of feature importance. | Q49: Class imbalance, Data availability, Model generalization | R49: To ensure student privacy and confidentiality, the researchers performed strict data anonymization, which involved the immediate removal and discarding of personal identifiers such as student names and CPF numbers at the commencement of the study.
A50: Predição de evasão no curso de Sistemas de Informação da UFSM utilizando dados históricos | B50: 10.5753/erbd.2026.20265 | C50: Dallanora, Leonardo and Mergen, Sérgio | D50: April 22, 2026 | E50: SBC OpenLib, 2026: Anais da XXI Escola Regional de Banco de Dados, SBC | F50: Brazil | G50: The primary contribution of this study is the design, implementation, and empirical validation of an Educational Data Mining (EDM) early warning framework that uses the Balanced Random Forest algorithm to forecast student dropout across multiple temporal advance windows (from 1 to 4 semesters prior to departure). By extracting key behavioral and academic indicators—such as grade volatility (standard deviation of grades), disengagement (course failure by frequency), and performance in 14 critical early-semester courses—the study demonstrates that high predictive precision (84,93% up to two years in advance and 92,32% in the semester immediately preceding dropout) can be achieved to enable proactive institutional retention interventions. | H50: The final analyzed dataset comprises historical academic records for 447 undergraduate students enrolled between 2009 and 2025 in the Information Systems program at UFSM, consisting of 298 dropout students (the majority class) and 149 graduated students (the minority class), after excluding zero-activity records and active regular students to prevent label ambiguity. | I50: In-person | J50: The monitored student attributes focus on internal academic performance and behavioral disengagement metrics, specifically grade consistency measured via the standard deviation of grades, course failure rates separated by grade (cognitive/content difficulty) versus attendance (behavioral disengagement), overall grade averages, and performance across 14 critical mandatory early-semester courses (such as Computer Organization, Calculus A, Digital Circuits, Programming Laboratory I, Discrete Mathematics, and Data Structures A). | K50: Academic records | L50: The primary classification algorithm evaluated in this work is the Balanced Random Forest Classifier, an ensemble machine learning model specifically designed to address class imbalance through dynamic under-sampling during tree construction. | M50: Ensemble learning | N50: Model efficacy was evaluated using overall Accuracy, Recall/Sensitivity (specifically measuring the proportion of correctly identified dropout students), and Precision/Assertiveness (measuring the reliability of positive dropout risk alerts), tracked across four distinct temporal observation windows (4, 3, 2, and 1 semester prior to dropout). | O50: The study provides quantitative results demonstrating high predictive performance that increases as student historical data consolidates: at 4 semesters of advance (2 years), the model achieves 75,94% accuracy, 72,21% sensitivity, and 84,93% precision; at 3 semesters, 78,68% accuracy, 77,02% sensitivity, and 89,98% precision; at 2 semesters, 79,99% accuracy, 77,62% sensitivity, and 89,66% precision; and at 1 semester prior to dropout (imminent scenario), it reaches 81,90% accuracy, 79,62% sensitivity, and 92,32% precision. | P50: The authors explicitly identify technical and contextual limitations, including a severe class imbalance inherent to historical transcripts (an approximate 2:1 ratio of dropouts to graduates), reduced model sensitivity when attempting long-term predictions (72,21% at 4 semesters compared to 79,62% at 1 semester), and the restriction of empirical evaluation to a single degree program at UFSM, necessitating future research to evaluate cross-institutional and multi-disciplinary generalizability. | Q50: Class imbalance, Model generalization | R50: The study utilized historical student transcripts provided by the course administration for academic research; however, the manuscript does not explicitly detail formal student informed consent procedures, institutional ethics committee approvals, or specific data anonymization and privacy protection mechanisms, representing partial compliance with SLR ethical guidelines.
... A52: Multidimensional Data Analysis and Effect Evaluation Model Construction of Practical Education Projects in Colleges and Universities | B52: 10.1109/IEHNS68708.2026.11606961 | C52: Xiao, Yan | D52: Date of Conference: 26-30 June 2026; Date Added to IEEE Xplore: 07 August 2026 | E52: Scopus, 2026 International Conference on Intelligent Engineering and Next-Gen Healthcare Systems (IEHNS), IEEE | F52: China | G52: The principal contribution of the study is the construction of a multidimensional data-driven effect evaluation model tailored for practical education projects in universities. The proposed framework fuses multi-source heterogeneous data (behavioral, performance, and process evaluation records), incorporates a combined weighting mechanism blending subjective Analytic Hierarchy Process (AHP) with objective Entropy Weighting Method (EWM), and leverages a machine learning regression model to accurately capture non-linear relationships, ultimately stratifying student outcomes into four performance tiers ("Excellent", "Good", "Medium", and "Needs Improvement") while significantly lowering evaluation RMSE from 0,083 to 0,042 and raising accuracy to 93,5%. | H52: The empirical evaluation was conducted using a dataset comprising 400 student samples participating in a university practical education project. | I52: Hybrid | J52: The monitored student variables encompass multi-dimensional attributes divided across knowledge ability, practical skills, innovative capabilities, and comprehensive quality metrics (including teamwork, operational task completion, independent exploration, and sense of responsibility). The dataset consists of multi-source heterogeneous student data structured into three primary categories: behavioral data (D1 captured from learning platform interactions), performance data (D2 reflecting grades and task outcomes), and process evaluation data (D3 comprising feedback records), which are standardized via Min-Max scaling and filtered through correlation matrix dimensionality reduction. | K52: Academic records, VLE activity log | L52: The framework applies a hybrid evaluation and prediction approach that integrates a combined subjective-objective linear weighting model (Entropy-AHP combination with adjustment parameter α) fed into a non-linear machine learning regression model optimized using a squared-error loss function and gradient descent parameter updates. | M52: Machine learning | N52: Model performance was rigorously evaluated across six quantitative metrics: Root Mean Square Error (RMSE), Coefficient of Determination (R²), Classification Accuracy (%), Standard Deviation of predictions, Computational Training Time (in seconds), and Generalization Error on validation subsets. | O52: The study provides quantitative empirical results demonstrating that the optimized fusion model achieved an RMSE of 0,042, an R² of 0,92, a classification accuracy of 93,5%, a standard deviation of 0,031, a training time of 7,4 seconds, and a generalization error of 0,051, outperforming baseline traditional weighted models (RMSE 0,083, Accuracy 78,6%) and single machine learning models (RMSE 0,061, Accuracy 84,3%); additionally, student evaluation scores stratified into 21,5% Excellent (n=86), 35,5% Good (n=142), 29,5% Average (n=118), and 13,5% Needs Improvement (n=54). | P52: The authors report technical and scope limitations, including a minor increase in computational training time (7,4 seconds), sensitivity to hyperparameter tuning such as the balance coefficient α and learning rate η, restricted empirical validation confined to 400 samples from a single academic institution, and lower student performance scores in innovative thinking relative to practical task execution. | Q52: Model generalization, Resource overhead | R52: The article does not report any ethical frameworks, privacy protection mechanisms, student consent procedures, data anonymization techniques, or institutional review board approvals associated with harvesting and analyzing student behavioral and academic platform data.
A53: Modeling Student–Project–Skill Interactions Using Graph Neural Networks for Enhanced Learning Analytics | B53: 10.59543/jidmis.v3.1379 | C53: Rao, Priya and Virdee, Bal and Rane, Nitin and Khanna, Ashish | D53: June 10, 2026 | E53: Scopus, Journal of Intelligent Decision Making and Information Science, Noves Ricerca | F53: India | G53: The primary contributions include the development of the SAS-GNN model, the formulation of a heterogeneous graph representation to map student-activity-skill interactions, and the integration of a GNNExplainer-based module to provide interpretable learning analytics. | H53: The research utilized the OULAD dataset encompassing 32.593 unique students, 173.912 assessment activity records, and 10.655.280 learner interaction records within the virtual learning environment. | I53: Online | J53: The monitored attributes include student demographic data, assessment results, course enrollment details, and behavioral/performance similarity features derived using Equation 3 (Cosine Similarity) to calculate the proximity between student feature vectors. | K53: Academic records, Demographic data, VLE activity log | L53: The primary model is the Student-Activity-Skill Graph Neural Network (SAS-GNN), which was benchmarked against the following baseline models: Logistic Regression, Random Forest, XGBoost, Multi-Layer Perceptron (MLP), Long Short-Term Memory (LSTM), Graph Convolutional Networks (GCN), GraphSAGE, and Graph Attention Networks (GAT). | M53: Deep learning | N53: The validation process utilized five quantitative metrics: Accuracy, Precision, Recall, F1-score, and ROC-AUC. | O53: The SAS-GNN model achieved a superior performance of 92,4% accuracy, a 0,915 F1-score, and a 0,946 ROC-AUC, representing a 2,3% accuracy improvement over the highest-performing baseline model (GAT). | P53: The authors identify historical limitations in the literature regarding the treatment of learners as independent observations; furthermore, their ablation study (Figure 5) reports that removing competency-based edges significantly degrades the model, resulting in a 3,5% performance drop for Student-Skill edges and a 2,8% drop for Activity-Skill relationships. | R53: The authors declare no competing interests and explicitly disclose the use of generative AI tools for language assistance during manuscript preparation, while emphasizing the use of a public repository for data transparency.
